{"v":2,"district":"Kwai Tsing","count":540,"fields":["id","name","name_en","lat","lng","address","district","district_tc","licence_type","expiry","endorsements"],"rows":[["fehd_2291000022","裕滿人家","Honorary Family",22.35772,114.12924,"新界葵涌石蔭路 地下64號鋪及 1字樓44-66號鋪","Kwai Tsing","葵青","General Restaurant","2026-06-30",[]],["fehd_2291000068","坤記粥品","坤記粥品",22.35987,114.1225,"新界葵涌 石蔭路94號地下","Kwai Tsing","葵青","General Restaurant","2026-06-30",[]],["fehd_2291000077","金來越南粉","金來越南粉",22.36264,114.12808,"新界葵涌 葵涌道1001號 德昌大廈內鋪13號","Kwai Tsing","葵青","General Restaurant","2026-06-30",[]],["fehd_2291000101","卡拉奇","KARACHI havAbite",22.36263,114.12106,"新界葵涌青山公路456號 屏麗徑葵豐大廈地下B座","Kwai Tsing","葵青","General Restaurant","2026-06-30",[]],["fehd_2291000110","復興粥麵家","復興粥麵家",22.36402,114.12586,"新界葵涌 荔景邨 日景樓地下S9鋪","Kwai Tsing","葵青","General Restaurant","2026-06-30",[]],["fehd_2291000129","仙花園餐廳","仙花園餐廳",22.36299,114.12431,"新界葵涌 葵盛邨第七座1號鋪","Kwai Tsing","葵青","General Restaurant","2026-06-30",[]],["fehd_2291000147","嘉年華酒家","Carnival Restaurant",22.35666,114.12375,"新界葵涌 荔景邨荔景酒樓地下至3樓","Kwai Tsing","葵青","General Restaurant","2026-06-30",[]],["fehd_2291000183","大光明飯店","大光明飯店",22.36042,114.12402,"新界葵涌葵涌道1001號 德昌大廈地下5號鋪","Kwai Tsing","葵青","General Restaurant","2026-06-30",[]],["fehd_2291000235","新聯發燒臘飯店","新聯發燒臘飯店",22.36332,114.124,"新界葵涌石蔭路107號 國寶樓地下C座","Kwai Tsing","葵青","General Restaurant","2026-06-30",[]],["fehd_2291000299","才興茶餐廳","才興茶餐廳",22.35595,114.12151,"新界葵涌 大白田街27號地下","Kwai Tsing","葵青","General Restaurant","2026-06-30",[]],["fehd_2291000323","阿媽無骨海南鸡","阿媽無骨海南鸡",22.36016,114.12337,"新界葵涌屏麗徑16號地下","Kwai Tsing","葵青","General Restaurant","2026-06-30",[]],["fehd_2291000332","喜悅皇宮","喜悅皇宮",22.36013,114.12717,"新界葵涌 青衣長康邨商場 地下(部份)及2樓","Kwai Tsing","葵青","General Restaurant","2026-06-30",[]],["fehd_2291000448","進美餐廳","進美餐廳",22.35785,114.12233,"新界葵涌 石英徑七號地下2號鋪","Kwai Tsing","葵青","General Restaurant","2026-06-30",[]],["fehd_2291000475","達成餐廳","達成餐廳",22.35873,114.12436,"新界下葵涌仁芳街7號 美豐大廈C座地下","Kwai Tsing","葵青","General Restaurant","2026-06-30",[]],["fehd_2291000484","發記廚房","Fat Kee Kitchen",22.36421,114.12682,"新界葵涌 光輝圍7號地下及閣樓","Kwai Tsing","葵青","General Restaurant","2026-06-30",[]],["fehd_2291000518","泰旺泰國小菜","泰旺泰國小菜",22.36321,114.1216,"新界葵涌 禾塘咀街127號地下","Kwai Tsing","葵青","General Restaurant","2026-06-30",[]],["fehd_2291000554","百份百餐廳","Hundred Percent Restaurant",22.3602,114.12907,"新界葵涌青衣 長康邨康泰樓地下7號鋪","Kwai Tsing","葵青","General Restaurant","2026-06-30",[]],["fehd_2291000563","大光明燒臘飯店","大光明燒臘飯店",22.36463,114.1278,"新界葵涌光輝里 萬成樓地下7號鋪","Kwai Tsing","葵青","General Restaurant","2026-06-30",[]],["fehd_2291000572","金椰林茶餐廳","金椰林茶餐廳",22.36419,114.12349,"新界葵涌 和宜合道132號地下","Kwai Tsing","葵青","General Restaurant","2026-06-30",[]],["fehd_2291000615","歡聚餐廳小廚","歡聚餐廳小廚",22.35522,114.12417,"新界葵涌 德士古道23號地下","Kwai Tsing","葵青","General Restaurant","2026-06-30",[]],["fehd_2291000642","德發鳳凰粥麵","德發鳳凰粥麵",22.35712,114.12967,"新界葵涌 德士古道25號地下","Kwai Tsing","葵青","General Restaurant","2026-06-30",[]],["fehd_2291000651","返尋味小廚","返尋味小廚",22.36244,114.12105,"新界葵涌 241地段和宜合道 瑞景大廈一樓11號鋪","Kwai Tsing","葵青","General Restaurant","2026-06-30",[]],["fehd_2291000703","麥當勞","MCDONALD'S",22.35524,114.12778,"新界葵涌和宜合道90-114號成城大廈地下9及10號鋪及1樓","Kwai Tsing","葵青","General Restaurant","2026-06-30",[]],["fehd_2291000712","葵芳閣龍寶酒家","葵芳閣龍寶酒家",22.35797,114.12439,"新界葵涌380地段 葵芳閣1樓(部份)","Kwai Tsing","葵青","General Restaurant","2026-06-30",[]],["fehd_2291000721","新龍騰閣燒臘飯店","新龍騰閣燒臘飯店",22.35919,114.12656,"新界葵涌青山公路452號 名賢大樓地下","Kwai Tsing","葵青","General Restaurant","2026-06-30",[]],["fehd_2291000730","蘭芳冰廳","蘭芳冰廳",22.3611,114.12392,"新界葵涌 高芳街27號地下","Kwai Tsing","葵青","General Restaurant","2026-06-30",[]],["fehd_2291000749","紅噹噹","HUNG DONG DONG",22.35723,114.12641,"新界葵涌 禾塘咀街123號地下(小部份)及 125號地下(南面部份)","Kwai Tsing","葵青","General Restaurant","2026-06-30",[]],["fehd_2291000767","永華園茶餐快餐廳","永華園茶餐快餐廳",22.35886,114.12533,"新界青衣 長康邨第五期 商場二期101號鋪","Kwai Tsing","葵青","General Restaurant","2026-06-30",[]],["fehd_2291000882","MCDONALD'S","MCDONALD'S",22.36392,114.12785,"新界青衣長發廣場4樓406-407號鋪","Kwai Tsing","葵青","General Restaurant","2026-06-30",[]],["fehd_2291000907","大家樂","Cafe De Coral",22.36322,114.1215,"新界葵涌葵涌廣場 1樓13-13A,15-18, 53-53A及55-59號鋪","Kwai Tsing","葵青","General Restaurant","2026-06-30",[]],["fehd_2291000916","美心MX","美心MX",22.36332,114.12364,"新界葵涌新葵興廣場2樓1A號鋪","Kwai Tsing","葵青","General Restaurant","2026-06-30",[]],["fehd_2291000925","港興燒味飯店","Kong Hing Siu Mei Restaurant",22.36277,114.12301,"新界葵涌青山公路470號鴻運大廈地下B鋪","Kwai Tsing","葵青","General Restaurant","2026-06-30",[]],["fehd_2291000943","大快活","FAIRWOOD FAST FOOD",22.35888,114.12596,"香港新界青衣 寮肚路6號長亨邨 長亨商場3樓324號鋪","Kwai Tsing","葵青","General Restaurant","2026-06-30",[]],["fehd_2291000989","煌宴","Euphoric Banquet",22.35927,114.12105,"新界葵涌葵興邨 葵興商場101號鋪","Kwai Tsing","葵青","General Restaurant","2026-06-30",[]],["fehd_2291000998","藝餐","藝餐",22.36068,114.12884,"新界葵涌葵涌廣場 1樓B21號鋪","Kwai Tsing","葵青","General Restaurant","2026-06-30",[]],["fehd_2291001177","凱悅茶餐廳","凱悅茶餐廳",22.35571,114.12113,"新界青衣青敬路77號 海悅花園地下3-6號鋪","Kwai Tsing","葵青","General Restaurant","2026-06-30",[]],["fehd_2291001247","MCDONALD'S","MCDONALD'S",22.36043,114.12344,"新界葵涌榮芳路1-5號 守運樓地下A鋪","Kwai Tsing","葵青","General Restaurant","2027-04-26",[]],["fehd_2291001283","金煌美食餐廳","金煌美食餐廳",22.36349,114.12367,"新界青衣清心街 新屋村地下1號鋪","Kwai Tsing","葵青","General Restaurant","2027-03-09",[]],["fehd_2291001292","金和林餐廳","金和林餐廳",22.35955,114.12985,"新界葵涌和宜合道162號 瑞景購物中心地下11及37號鋪","Kwai Tsing","葵青","General Restaurant","2027-05-14",[]],["fehd_2291001353","金豐粉麵咖啡店","金豐粉麵咖啡店",22.35597,114.12568,"新界青衣長康邨 康美樓與康順樓交界 商場第二期3字樓1號鋪","Kwai Tsing","葵青","General Restaurant","2027-05-30",[]],["fehd_2291001414","雅殿海鮮酒家","ELEGANT SEAFOOD RESTAURANT",22.35675,114.12594,"新界青衣長青邨 長青商場平台地下及1樓","Kwai Tsing","葵青","General Restaurant","2026-07-03",[]],["fehd_2291001432","鴻發餐廳","HUNG FAT CONGEE & NOODLE",22.36228,114.1212,"新界葵涌麗瑤邨 麗瑤商場地下9-10號鋪","Kwai Tsing","葵青","General Restaurant","2026-08-24",[]],["fehd_2291001478","祥發茶餐廳","祥發茶餐廳",22.35528,114.12757,"新界青衣 青綠街7-19號 青怡花園地下14-16號鋪","Kwai Tsing","葵青","General Restaurant","2027-02-15",[]],["fehd_2291001487","葵涌恒景龍寶酒家","葵涌恒景龍寶酒家",22.36154,114.12473,"新界葵涌榮芳路9號 恒景商場2字樓201-204號鋪","Kwai Tsing","葵青","General Restaurant","2027-02-23",[]],["fehd_2291001511","MCDONALD'S","MCDONALD'S",22.3609,114.12004,"新界青衣長康邨 長康商場1期地下101號鋪","Kwai Tsing","葵青","General Restaurant","2027-01-13",[]],["fehd_2291001566","太興","TAI HING",22.35594,114.12604,"新界青衣楓樹窩路1號 翠怡商場三期地下304-305號鋪","Kwai Tsing","葵青","General Restaurant","2027-04-21",[]],["fehd_2291001663","肯德基","KFC",22.35583,114.12963,"新界青衣 青衣城第3層301號鋪","Kwai Tsing","葵青","General Restaurant","2026-11-02",[]],["fehd_2291001733","金寶飯店","金寶飯店",22.35911,114.12428,"新界葵涌石蔭路135-147號 葵寶大廈地下5A及11A鋪","Kwai Tsing","葵青","General Restaurant","2027-03-05",[]],["fehd_2291001751","McDonald's","McDonald's",22.36209,114.12418,"新界葵涌葵盛東邨 葵盛東商場1樓105號鋪","Kwai Tsing","葵青","General Restaurant","2026-06-20",[]],["fehd_2291001812","富華冰室","富華冰室",22.3605,114.12324,"新界葵涌 葵富路7-11號 葵涌廣場地下A17號鋪","Kwai Tsing","葵青","General Restaurant","2026-09-07",[]],["fehd_2291001821","蕃茄工房","蕃茄工房",22.35887,114.12383,"新界青衣青綠街1號偉景花園商場1字樓102-104號鋪","Kwai Tsing","葵青","General Restaurant","2026-09-15",[]],["fehd_2291001919","BANGKOK BBQ","BANGKOK BBQ",22.35793,114.12382,"新界青衣美景花園7座 第3層91及112號鋪","Kwai Tsing","葵青","General Restaurant","2027-02-22",[]],["fehd_2291001937","金寶茶餐廳","金寶茶餐廳",22.35896,114.12103,"新界青衣青裕新村5號 地下及鋪前座位間","Kwai Tsing","葵青","General Restaurant","2027-03-22",["Outside Seating"]],["fehd_2291001982","俊達晞茶餐廳小廚","俊達晞茶餐廳小廚",22.36034,114.12737,"新界青衣 青綠街7-19號 青怡商場1字樓12-13號鋪","Kwai Tsing","葵青","General Restaurant","2026-07-30",[]],["fehd_2291001991","銀龍粉麵茶餐廳","銀龍粉麵茶餐廳",22.3627,114.12598,"新界葵涌石蔭邨 石蔭商場地下9號鋪","Kwai Tsing","葵青","General Restaurant","2026-08-01",[]],["fehd_2291002000","壹滙中菜廳","ONE CUISINE",22.35697,114.12655,"新界青衣青敬路33號 青衣城地下G04號鋪","Kwai Tsing","葵青","General Restaurant","2026-08-12",[]],["fehd_2291002055","潮庭 / 北京樓","潮庭 / 北京樓",22.35701,114.12488,"新界葵涌 新都會廣場第5層511-530鋪","Kwai Tsing","葵青","General Restaurant","2026-10-02",["Sashimi","Sushi"]],["fehd_2291002107","百匯酒家","Deluxe Restaurant",22.35541,114.12456,"新界葵涌石蔭邨 石蔭商場地下11號鋪","Kwai Tsing","葵青","General Restaurant","2027-01-11",[]],["fehd_2291002125","馬記","馬記",22.36419,114.12604,"新界葵涌石蔭路19號 成城大廈地下1號鋪","Kwai Tsing","葵青","General Restaurant","2027-01-23",[]],["fehd_2291002198","唯一麵家","唯一麵家",22.35793,114.12894,"新界葵涌 葵富路7-11號 葵涌廣場地下A77號鋪(主要部份)","Kwai Tsing","葵青","General Restaurant","2026-06-28",[]],["fehd_2291002213","富華冰室","富華冰室",22.36409,114.12532,"新界葵涌葵富路7-11號 葵涌廣場地下 A63A (主要部份) A65及A66鋪","Kwai Tsing","葵青","General Restaurant","2026-07-02",[]],["fehd_2291002231","MCDONALD'S","MCDONALD'S",22.35615,114.12854,"新界葵涌葵昌路56號貿易之都1字樓1號鋪","Kwai Tsing","葵青","General Restaurant","2026-08-04",[]],["fehd_2291002277","MCDONALD'S","MCDONALD'S",22.36379,114.12951,"新界青衣楓樹窩路 翠怡花園商場地下G2號鋪","Kwai Tsing","葵青","General Restaurant","2026-11-26",[]],["fehd_2291002286","賓墟冰室","賓墟冰室",22.36286,114.12694,"新界青衣 牙鷹洲街8號 灝景灣商場第1層1號鋪","Kwai Tsing","葵青","General Restaurant","2027-02-13",[]],["fehd_2291002426","穆德廚房","Haq  Restaurant",22.3602,114.12626,"新界葵涌屏麗徑4,6及16號 名賢大樓地下6A號鋪","Kwai Tsing","葵青","General Restaurant","2027-01-09",[]],["fehd_2291002462","福林餐廳","福林餐廳",22.36492,114.12606,"新界葵涌 石蔭路88號地下","Kwai Tsing","葵青","General Restaurant","2027-01-25",[]],["fehd_2291002505","耀記滷水飯店","耀記滷水飯店",22.35891,114.12714,"新界青衣 大王下村25號地下","Kwai Tsing","葵青","General Restaurant","2026-06-02",[]],["fehd_2291002541","源興燒味小館","源興燒味小館",22.36038,114.12068,"新界葵涌 禾塘咀街109-115號高層地下","Kwai Tsing","葵青","General Restaurant","2026-09-23",["Raw Meat","Raw Oysters","Sashimi","Sushi"]],["fehd_2291002587","阿家一町","Wendy's Kitchen",22.36189,114.12968,"新界葵涌敬祖路6號祖堯邨E座地下11-12號鋪","Kwai Tsing","葵青","General Restaurant","2027-01-20",[]],["fehd_2291002596","榮發燒味茶餐廳","榮發燒味茶餐廳",22.3617,114.12287,"新界葵涌石籬邨 石籬商場2期2樓236號鋪","Kwai Tsing","葵青","General Restaurant","2027-03-02",[]],["fehd_2291002602","岱民石蔭店","岱民石蔭店",22.35727,114.12481,"新界葵涌和宜合道154-156號地下","Kwai Tsing","葵青","General Restaurant","2027-05-09",[]],["fehd_2291800167","重慶小面皇","重慶小面皇",22.36009,114.1268,"新界葵涌葵涌道1001號 德昌大廈地下26D1A鋪","Kwai Tsing","葵青","General Restaurant","2026-08-24",["Sashimi","Sushi"]],["fehd_2291800325","如富上海麵館","如富上海麵館",22.36468,114.12716,"新界葵涌 葵興路102號 葵涌中心地下A21及A22號鋪","Kwai Tsing","葵青","General Restaurant","2026-11-30",[]],["fehd_2291800398","四季餐廳","四季餐廳",22.36162,114.12757,"新界葵涌葵涌邨 葵涌商場108號鋪","Kwai Tsing","葵青","General Restaurant","2027-03-08",["Sashimi","Sushi"]],["fehd_2291800404","大家樂","Cafe de Coral",22.35829,114.12965,"新界葵涌 葵涌商場第一層 平台122號鋪","Kwai Tsing","葵青","General Restaurant","2027-03-13",[]],["fehd_2291800459","木星薈","JUPITER GATHERING CAFÉ",22.35808,114.12239,"新界葵涌石英徑2-10號 及石文徑1號葵英樓 地下G10鋪","Kwai Tsing","葵青","General Restaurant","2027-05-02",["Raw Oysters","Sashimi","Sushi"]],["fehd_2291800486","食得喜麵家","食得喜麵家",22.35966,114.12601,"新界青衣細山路2-16號 美景花園第二期 第三層110-111鋪","Kwai Tsing","葵青","General Restaurant","2026-06-21",[]],["fehd_2291800510","小磨菇冰室","Mushroom Express",22.36051,114.12605,"新界葵涌 青山公路456-458號 葵豐樓地下H鋪","Kwai Tsing","葵青","General Restaurant","2027-07-06",[]],["fehd_2291800556","海港薈","Victoria Harbour Supreme",22.36004,114.12294,"新界青衣青敬路33號 青衣城310A鋪","Kwai Tsing","葵青","General Restaurant","2026-08-14",[]],["fehd_2291800565","大快活","Fairwood Fast Food",22.35863,114.12457,"新界青衣翠怡花園 商業中心第二期1字樓101號鋪","Kwai Tsing","葵青","General Restaurant","2026-08-17",[]],["fehd_2291800574","牧羊少年咖啡館","The Alchemist Caf'e",22.35648,114.12559,"新界葵涌興寧路12號地下葵青劇院2號鋪及露天座位","Kwai Tsing","葵青","General Restaurant","2026-08-22",[]],["fehd_2291800608","椰林閣餐廳","Yeh Lam Kwok Restaurant",22.36255,114.1201,"新界葵涌葵涌邨 葵涌商場第1層123號鋪","Kwai Tsing","葵青","General Restaurant","2026-09-19",[]],["fehd_2291800626","廣東燒味餐廳","廣東燒味餐廳",22.3606,114.12957,"新界葵涌盛芳街21號 興芳路188-190號智芳街1-3號 協德大廈地下12號鋪","Kwai Tsing","葵青","General Restaurant","2026-11-07",[]],["fehd_2291800705","泛亞飲食","Asia Pacific",22.35506,114.12124,"新界葵涌瑪嘉烈醫院路 瑪嘉烈醫院G座4字樓職員食堂","Kwai Tsing","葵青","General Restaurant","2027-04-24",[]],["fehd_2291800741","耀記粥店","耀記粥店",22.35625,114.12593,"新界葵涌大隴街113-127號昌盛樓地下115號鋪","Kwai Tsing","葵青","General Restaurant","2026-07-22",[]],["fehd_2291800787","銀城餐廳","銀城餐廳",22.35644,114.12872,"新界葵涌和宜合道166號 瑞景大廈地下9號鋪","Kwai Tsing","葵青","General Restaurant","2026-09-19",[]],["fehd_2291800796","太子小廚餐廳","太子小廚餐廳",22.36082,114.12243,"新界葵涌青山公路葵涌段432-436號 偉賢樓地下A1-B1號鋪","Kwai Tsing","葵青","General Restaurant","2026-12-16",[]],["fehd_2291800811","翠湖茶餐廳","翠湖茶餐廳",22.36022,114.12245,"新界青衣 長康邨商場二期 3樓306及307號鋪","Kwai Tsing","葵青","General Restaurant","2027-01-03",[]],["fehd_2291800839","家家樂餐廳","家家樂餐廳",22.36472,114.12527,"新界葵涌大隴街107-109號 昌榮樓地下3號鋪","Kwai Tsing","葵青","General Restaurant","2027-02-27",[]],["fehd_2291800909","前田町壽司和食","Kanjo Japanese Cuisine",22.35741,114.12996,"新界青衣細山路2-16號 美景花園第3層38號鋪","Kwai Tsing","葵青","General Restaurant","2026-07-20",["Sashimi","Sushi"]],["fehd_2291800927","穩記茶餐廳","WAN KEE RESTAURANT",22.35602,114.12476,"新界青衣長宏邨 長宏商場5號鋪","Kwai Tsing","葵青","General Restaurant","2026-08-18",[]],["fehd_2291801027","Beans","Beans",22.36412,114.12189,"新界葵涌興芳路223號新都會廣場第1層135號鋪","Kwai Tsing","葵青","General Restaurant","2027-02-15",["Sashimi","Sushi"]],["fehd_2291801045","一粥麵","Super Super",22.35875,114.12639,"新界葵涌葵涌商場110號鋪","Kwai Tsing","葵青","General Restaurant","2027-03-03",[]],["fehd_2291801106","譚仔雲南米線","譚仔雲南米線",22.36046,114.12208,"新界葵涌葵義路2-10號好爵中心地下49-54號鋪","Kwai Tsing","葵青","General Restaurant","2027-04-08",[]],["fehd_2291801115","永利餐廳","永利餐廳",22.35869,114.12209,"新界荃灣德士古道53號地下","Kwai Tsing","葵青","General Restaurant","2027-05-19",[]],["fehd_2291801133","彩龍船中西美食坊","LUCKY DRAGON BOAT DELICIOUS FOOD",22.35632,114.12722,"新界葵涌敬祖路6號祖堯坊商場2樓E座201號鋪","Kwai Tsing","葵青","General Restaurant","2026-06-11",[]],["fehd_2291801160","銀龍粉麵茶餐廳","Ngan Lung Restaurant",22.3601,114.12841,"新界葵涌葵芳邨葵芳商場一樓112B-C號鋪","Kwai Tsing","葵青","General Restaurant","2027-07-05",[]],["fehd_2291801179","勝康餐廳","勝康餐廳",22.36419,114.12094,"新界葵涌青山公路474號地下","Kwai Tsing","葵青","General Restaurant","2026-07-07",[]],["fehd_2291801212","金潮小廚","金潮小廚",22.36189,114.12093,"新界葵涌榮芳路9號恒景商場 地下G02, G14及G15號鋪","Kwai Tsing","葵青","General Restaurant","2026-08-10",[]],["fehd_2291801221","鴻苑魚蛋粉麵","鴻苑魚蛋粉麵",22.36259,114.12473,"新界葵涌石蔭路61-83號金祿樓地下8號鋪","Kwai Tsing","葵青","General Restaurant","2026-08-18",[]],["fehd_2291801276","香港仔魚蛋王","香港仔魚蛋王",22.36367,114.12547,"新界葵涌盛芳街23/29及33/39號勝華大廈地下及閣樓B鋪","Kwai Tsing","葵青","General Restaurant","2026-10-20",[]],["fehd_2291801300","港龍茶餐廳","KONG LUNG RESTAURANT",22.36332,114.12768,"新界葵涌大隴街107號昌榮樓後街地下低層4號鋪","Kwai Tsing","葵青","General Restaurant","2026-12-06",[]],["fehd_2291801328","麥當勞餐廳","McDonald's Restaurant",22.36067,114.12453,"新界葵涌石蔭邨石蔭商場低層地下2字樓 LG213及LG214號鋪","Kwai Tsing","葵青","General Restaurant","2027-01-06",[]],["fehd_2291801337","大快活快餐","Fairwood Fast Food",22.35505,114.12374,"新界葵涌葵芳邨葵芳商場一樓125-130號鋪","Kwai Tsing","葵青","General Restaurant","2027-01-17",[]],["fehd_2291801355","秀吉食堂","秀吉食堂",22.35967,114.12776,"新界青衣細山路2-16號美景花園第九座 第三層107及113號鋪","Kwai Tsing","葵青","General Restaurant","2027-02-04",["Sashimi","Sushi"]],["fehd_2291801364","MX/Port Spot","MX/Port Spot",22.35681,114.12135,"新界青衣担杆山路6號長發邨長發廣場2樓224及225號鋪","Kwai Tsing","葵青","General Restaurant","2027-03-11",[]],["fehd_2291801373","一粥麵","Super Super",22.36053,114.12755,"新界青衣担杆山路6號長發商場3樓319號鋪","Kwai Tsing","葵青","General Restaurant","2027-05-05",[]],["fehd_2291801391","脆味批","CHUBBY'S PIZZA",22.36488,114.12356,"新界葵涌葵芳商場地下4及5號鋪","Kwai Tsing","葵青","General Restaurant","2026-06-16",[]],["fehd_2291801425","吉野家","Yoshinoya",22.36146,114.12331,"新界葵涌葵富路7-11號葵涌廣場3樓304號鋪","Kwai Tsing","葵青","General Restaurant","2026-07-22",[]],["fehd_2291801461","東裕燒腊飯店","東裕燒腊飯店",22.36351,114.12307,"新界葵涌葵興邨葵興商場地下8號鋪","Kwai Tsing","葵青","General Restaurant","2026-09-12",[]],["fehd_2291801470","茶悅","Lovely Tea",22.35933,114.12805,"新界葵涌石蔭邨石蔭商場LG2樓LG205-206號鋪","Kwai Tsing","葵青","General Restaurant","2026-10-12",["Sashimi","Sushi"]],["fehd_2291801522","新港宴會廳","Sun Kong Restaurant",22.35763,114.12576,"新界葵涌和宜合道33號雍雅軒地下","Kwai Tsing","葵青","General Restaurant","2026-12-08",[]],["fehd_2291801531","御龍軒","御龍軒",22.35562,114.12295,"新界葵涌葵昌路51號九龍貿易中心第三層","Kwai Tsing","葵青","General Restaurant","2026-12-23",[]],["fehd_2291801540","香港中華基督教青年會新界會所餐廳","CHINESE YMCA OF HONG KONG NT CENTRE CAFE",22.35509,114.12207,"新界葵涌KCTL321葵盛圍32-40號地下A01室","Kwai Tsing","葵青","General Restaurant","2027-01-02",[]],["fehd_2291801559","兄弟快餐店","兄弟快餐店",22.36276,114.12602,"新界葵涌葵涌道1001號德昌大廈地下7號鋪","Kwai Tsing","葵青","General Restaurant","2027-01-30",[]],["fehd_2291801610","糯米泰","糯米泰",22.36224,114.12899,"新界葵涌光輝圍39號A昌偉大廈地下29號鋪","Kwai Tsing","葵青","General Restaurant","2026-06-19",[]],["fehd_2291801629","ITAMOMO CAFE & R.U.D","ITAMOMO CAFE & R.U.D",22.3594,114.12141,"新界青衣担杆山路6號長發廣場第3層321C號鋪","Kwai Tsing","葵青","General Restaurant","2026-06-21",[]],["fehd_2291801647","尚品小厨","尚品小厨",22.35593,114.12637,"新界葵涌石蔭路61-83號金祿樓地下7號鋪","Kwai Tsing","葵青","General Restaurant","2026-06-28",[]],["fehd_2291801656","榮康燒臘茶餐","榮康燒臘茶餐",22.36024,114.12912,"新界青衣長康邨第一商場地下1,3,4號熟食亭","Kwai Tsing","葵青","General Restaurant","2026-08-01",[]],["fehd_2291801665","山下無雙日式料理","Unique Sushi",22.35563,114.12375,"新界葵涌大隴街103號昌榮樓地下1號鋪","Kwai Tsing","葵青","General Restaurant","2026-08-10",["Sashimi","Sushi"]],["fehd_2291801708","滋味無窮","AROY DEE THAI",22.36289,114.12589,"新界葵涌屏麗徑5-11號葵豐樓地下I1號鋪","Kwai Tsing","葵青","General Restaurant","2026-09-22",[]],["fehd_2291801717","稻香","Tao Heung",22.36311,114.12619,"新界青衣楓樹窩路1號翠怡商場2期1樓103至115號鋪","Kwai Tsing","葵青","General Restaurant","2026-10-06",["Sashimi","Sushi"]],["fehd_2291801726","六記","六記",22.36172,114.12623,"新界青衣涌尾村92號地下","Kwai Tsing","葵青","General Restaurant","2026-10-20",[]],["fehd_2291801735","東海薈•拉斐特","East Ocean Lafayette",22.35506,114.12208,"新界青衣青衣城1字樓117號鋪","Kwai Tsing","葵青","General Restaurant","2026-11-17",["Sashimi"]],["fehd_2291801762","長旺鹵味大王","長旺鹵味大王",22.35502,114.12232,"新界葵涌盛芳街17-19號京寶大廈地下A7號鋪","Kwai Tsing","葵青","General Restaurant","2027-01-08",[]],["fehd_2291801771","譚仔三哥米線","譚仔三哥米線",22.36109,114.12997,"新界葵涌大窩口道大窩口邨大窩口商場(I)地下A07號鋪","Kwai Tsing","葵青","General Restaurant","2027-01-12",[]],["fehd_2291801780","百佳咖啡","Pokka Cafe",22.35767,114.12251,"新界青衣青敬路33號青衣城第二層201號鋪","Kwai Tsing","葵青","General Restaurant","2027-01-15",["Sashimi","Sushi"]],["fehd_2291801814","華豐餐廳小廚","華豐餐廳小廚",22.36174,114.12179,"新界葵涌下葵涌邨地下31室","Kwai Tsing","葵青","General Restaurant","2027-01-29",[]],["fehd_2291801869","Dragon Delicious","龍廷粵菜廳",22.36185,114.12737,"新界葵涌荔景袓堯邨袓堯中心F座F16及116號鋪","Kwai Tsing","葵青","General Restaurant","2026-06-03",[]],["fehd_2291801878","肯德基","K F C",22.36274,114.12468,"新界葵涌榮芳路9號恒景花園恒景商場地下G06-07號舖","Kwai Tsing","葵青","General Restaurant","2026-06-27",[]],["fehd_2291801887","泰寫意","泰寫意",22.35764,114.12255,"新界葵涌葵盛西邨商場三樓第28號舖","Kwai Tsing","葵青","General Restaurant","2026-08-13",[]],["fehd_2291801939","富臨酒家","FOO LUM RESTAURANT",22.35646,114.1237,"新界葵涌和宜合道26-30號地下A鋪","Kwai Tsing","葵青","General Restaurant","2027-01-13",["Raw Meat","Raw Oysters","Sashimi","Sushi"]],["fehd_2291801957","樂芝食坊鮮魚湯米線","樂芝食坊鮮魚湯米線",22.35762,114.12847,"新界葵涌光輝圍39A昌偉大廈地下26號鋪","Kwai Tsing","葵青","General Restaurant","2027-01-16",[]],["fehd_2291801966","韓餐","韓餐",22.35781,114.12883,"新界青衣細山路2至16號美景花園第三層72至73及76至77 號鋪","Kwai Tsing","葵青","General Restaurant","2027-01-21",[]],["fehd_2291801975","譽居(青衣分店)","PRAISE HOUSE CONGEE & NOODLE CUISINE",22.35562,114.12298,"新界青衣青衣城商場地下G03B鋪","Kwai Tsing","葵青","General Restaurant","2027-01-28",[]],["fehd_2291801993","雲桂香","雲桂香",22.36448,114.12092,"新界葵涌信芳街10號地下","Kwai Tsing","葵青","General Restaurant","2027-02-18",[]],["fehd_2291802002","Mr. Steak","Mr. Steak",22.36208,114.12222,"新界青衣青敬路33號青衣城地下G03A號舖","Kwai Tsing","葵青","General Restaurant","2027-02-28",["Raw Oysters","Sashimi"]],["fehd_2291802020","大家樂 & 一粥麵","Café de Coral & Super Super",22.35831,114.12131,"新界青衣青衣路1號 藍澄灣平台第一層2A及2B號鋪(A部份)","Kwai Tsing","葵青","General Restaurant","2027-05-14",[]],["fehd_2291802048","新四眼佬打冷小廚","新四眼佬打冷小廚",22.36041,114.12402,"新界葵涌榮芳路107及109號舖地下","Kwai Tsing","葵青","General Restaurant","2026-06-05",[]],["fehd_2291802066","荷里活冰室","荷里活冰室",22.35844,114.12162,"新界青衣青綠街7-19號青怡花園地下4-7號鋪","Kwai Tsing","葵青","General Restaurant","2026-07-04",[]],["fehd_2291802075","食樂","SNOW",22.35628,114.1201,"新界葵涌美芳街1號 美寧大廈1B號鋪地下及閣樓","Kwai Tsing","葵青","General Restaurant","2026-07-09",[]],["fehd_2291802109","葵盛西龍順軒海鮮酒家","Kwai Shing West Lung Shun Hin Seafood Restaurant",22.35925,114.12194,"新界葵涌葵盛西邨葵盛西商場一樓32至33號鋪","Kwai Tsing","葵青","General Restaurant","2027-01-15",[]],["fehd_2291802118","金樹林燒臘飯店","金樹林燒臘飯店",22.36098,114.12609,"新界葵涌石宜路6號地下","Kwai Tsing","葵青","General Restaurant","2027-01-27",[]],["fehd_2291802127","南豐餐廳","南豐餐廳",22.35516,114.12216,"新界葵涌景荔徑8號盈暉臺家居中心1樓120號鋪","Kwai Tsing","葵青","General Restaurant","2027-01-28",[]],["fehd_2291802136","Euro Go Go","Euro Go Go",22.35822,114.12101,"新界葵涌興芳路223號新都會廣場1樓168-171號鋪","Kwai Tsing","葵青","General Restaurant","2027-02-04",[]],["fehd_2291802154","新豐記","新豐記",22.36428,114.12975,"新界葵涌信芳街39及39A號悅龍大廈地下","Kwai Tsing","葵青","General Restaurant","2027-02-05",[]],["fehd_2291802172","新泰國廚房","KONGPIM THAILAND FOOD",22.35535,114.12159,"新界葵涌打磚坪街1-25號寶星中心地下低層1號舖","Kwai Tsing","葵青","General Restaurant","2027-03-13",[]],["fehd_2291802181","廣興粥店","廣興粥店",22.35856,114.12522,"新界葵涌葵涌道1001號德昌大厦地下26D-1鋪","Kwai Tsing","葵青","General Restaurant","2027-03-27",[]],["fehd_2291802215","雲貴軒","THE VERMICELLI HOUSE",22.36278,114.12068,"新界葵涌葵芳邨葵芳廣場1樓111及111A號鋪","Kwai Tsing","葵青","General Restaurant","2027-05-07",[]],["fehd_2291802233","稻田食堂","INADA SHOKUDO",22.36098,114.12064,"新界葵涌仁芳街12號美豐大廈地下6號鋪","Kwai Tsing","葵青","General Restaurant","2026-06-17",["Sashimi","Sushi"]],["fehd_2291802251","信芳廚","SHUN FONG RESTAURANT",22.3582,114.12165,"新界葵涌信芳街30至42號豪勝閣地下F鋪及鋪前露天座位","Kwai Tsing","葵青","General Restaurant","2026-08-18",["Outside Seating"]],["fehd_2291802260","翠苑餐廳","Tsui Yuen Restaurant",22.35882,114.12716,"新界青衣美景花園3樓115及116號鋪","Kwai Tsing","葵青","General Restaurant","2026-09-10",[]],["fehd_2291802279","港龍茶餐廳","港龍茶餐廳",22.36126,114.12354,"新界葵涌石蘺邨石寧樓地下1號鋪","Kwai Tsing","葵青","General Restaurant","2026-09-23",[]],["fehd_2291802288","荃福樓","Tsuen Fu Lou",22.36489,114.12278,"新界葵涌青山公路659號1樓(部分)","Kwai Tsing","葵青","General Restaurant","2026-10-19",["Sashimi","Sushi"]],["fehd_2291802297","Dorsett Café","Dorsett Café",22.3601,114.12967,"新界葵涌健全街28號地下(部份)","Kwai Tsing","葵青","General Restaurant","2026-10-21",["Sashimi","Sushi"]],["fehd_2291802330","薩莉亞意式餐廳","Saizeriya Italian Restaurant",22.36438,114.12214,"新界葵涌梨木道120號石蔭邨石蔭商場LG2樓201號鋪","Kwai Tsing","葵青","General Restaurant","2026-12-01",[]],["fehd_2291802349","俊達信茶餐廳小廚","俊達信茶餐廳小廚",22.36271,114.12369,"新界葵涌青山公路416號葵星中心地下低層50-51號 及56-57號鋪","Kwai Tsing","葵青","General Restaurant","2026-12-07",["Sashimi","Sushi"]],["fehd_2291802376","吉野家","Yoshinoya",22.36156,114.12871,"新界青衣担杆山路6號長發邨長發廣場3樓313,314,315 及316號鋪","Kwai Tsing","葵青","General Restaurant","2027-01-22",[]],["fehd_2291802385","大快活快餐","Fairwood Fast Food",22.36257,114.12157,"新界青衣美景花園L3層5-9, 15-16及21號鋪","Kwai Tsing","葵青","General Restaurant","2027-02-01",[]],["fehd_2291802394","必勝客","Pizza Hut",22.36293,114.12504,"新界葵涌石籬和宜合道26號和宜商場LG2","Kwai Tsing","葵青","General Restaurant","2027-02-16",[]],["fehd_2291802419","新豐","SUN FUNG",22.36116,114.12401,"新界葵涌禮芳街23號葵福大廈地下3號鋪","Kwai Tsing","葵青","General Restaurant","2027-03-30",[]],["fehd_2291802428","泰星匯泰國菜","Thai Sparkle Food",22.36218,114.12448,"新界葵涌信芳街30,36,40,42號濠勝閣地下D鋪","Kwai Tsing","葵青","General Restaurant","2027-04-09",[]],["fehd_2291802437","天月居","天月居",22.35692,114.12792,"新界葵涌葵昌路51號九龍貿易中心2樓閣樓M03舖","Kwai Tsing","葵青","General Restaurant","2027-04-29",[]],["fehd_2291802455","胡椒廚房","Pepper Lunch",22.35768,114.12849,"新界葵涌興芳路223號新都會廣場2層275至276號鋪","Kwai Tsing","葵青","General Restaurant","2027-05-20",[]],["fehd_2291802464","麥當勞餐廳","McDonald's Restaurant",22.35558,114.12212,"新界葵涌葵涌道1001號德昌大廈 一樓3號鋪","Kwai Tsing","葵青","General Restaurant","2027-06-03",[]],["fehd_2291802482","香葉灣","香葉灣",22.35779,114.12239,"新界葵涌葵昌路51號九龍貿易中心1座2樓S3號鋪","Kwai Tsing","葵青","General Restaurant","2026-06-21",["Sashimi","Sushi"]],["fehd_2291802491","百份百餐廳","CAFE 100%",22.35755,114.12474,"新界葵涌大窩口道15號大窩口邨 大窩口商場(II)期地下6號鋪(A部份)","Kwai Tsing","葵青","General Restaurant","2026-06-22",[]],["fehd_2291802534","譚仔三哥米線","譚仔三哥米線",22.35831,114.12574,"新界葵涌葵昌路51號九龍貿易中心2樓閣樓M01號鋪","Kwai Tsing","葵青","General Restaurant","2026-07-23",[]],["fehd_2291802543","百份百餐廳","Hundred Percent Restaurant",22.35674,114.12645,"新界葵涌華景山路9號華景商場地下20號鋪(A部份)","Kwai Tsing","葵青","General Restaurant","2026-07-27",[]],["fehd_2291802589","Mos Burger","Mos Burger",22.36398,114.12654,"新界青衣擔杆山路6號長發邨長發廣場 二樓203及203A號鋪","Kwai Tsing","葵青","General Restaurant","2026-08-17",[]],["fehd_2291802622","震陞雲南飲食","震陞雲南飲食",22.36424,114.12024,"新界葵涌信芳街35及37號葵福大廈地下1及2號鋪","Kwai Tsing","葵青","General Restaurant","2026-09-29",[]],["fehd_2291802640","石籬粉仔","石籬粉仔",22.36115,114.1287,"新界葵涌大隴街129-151號葵都大廈地下5鋪","Kwai Tsing","葵青","General Restaurant","2026-10-19",[]],["fehd_2291802677","寶膳美點火鍋小廚","寶膳美點火鍋小廚",22.35521,114.12371,"新界葵涌麗瑤邨街市地下2號鋪","Kwai Tsing","葵青","General Restaurant","2026-11-03",[]],["fehd_2291802686","大家樂","Cafe de Coral",22.3624,114.12959,"新界青衣楓樹窩路10號青衣邨青衣邨商場地下S3鋪","Kwai Tsing","葵青","General Restaurant","2026-11-05",[]],["fehd_2291802695","譚仔雲南米線","譚仔雲南米線",22.36185,114.12552,"新界青衣楓樹窩路1號翠怡商場二期一樓 116-118及123號鋪","Kwai Tsing","葵青","General Restaurant","2026-11-17",[]],["fehd_2291802701","葵線軒","葵線軒",22.36309,114.1217,"新界葵涌大隴街153號怡勝花園地下1A及1B鋪","Kwai Tsing","葵青","General Restaurant","2026-11-25",[]],["fehd_2291802747","銀河美食屋","銀河美食屋",22.35545,114.12901,"新界葵涌美芳街4號昌鴻大廈地下8鋪","Kwai Tsing","葵青","General Restaurant","2027-01-13",[]],["fehd_2291802765","雲在線小鍋米線紅薯粉","Noodle Online",22.35837,114.12244,"新界葵涌榮芳路97-111號葵祥大廈地下及閣樓C鋪","Kwai Tsing","葵青","General Restaurant","2027-02-11",[]],["fehd_2291802774","叉燒丼家(3)","The Master of Char Siu",22.35862,114.12705,"新界葵涌和宜合道26-30號和宜商場地下B及C鋪","Kwai Tsing","葵青","General Restaurant","2027-02-14",[]],["fehd_2291802792","金園餐廳","金園餐廳",22.3605,114.12048,"新界葵涌大廈街5-17號仁雅大廈地下及閣樓B鋪","Kwai Tsing","葵青","General Restaurant","2027-03-01",[]],["fehd_2291802808","源記餐廳","Yuen Kee Restaurant",22.36473,114.12299,"新界葵涌葵義路15號葵芳閣地下C1及C2鋪","Kwai Tsing","葵青","General Restaurant","2027-03-31",[]],["fehd_2291802835","麥當勞餐廳","McDonald's Restaurant",22.36062,114.12991,"新界青衣長亨邨長亨商場3樓321-323號鋪","Kwai Tsing","葵青","General Restaurant","2027-05-16",[]],["fehd_2291802844","紫宸","P.AM",22.36402,114.12057,"新界葵涌榮芳路9號恒景商場恒景花園地下商業單位G12號","Kwai Tsing","葵青","General Restaurant","2027-05-19",[]],["fehd_2291802853","奶茶咖啡室有限公司","TEA & COFFEE CAFE LIMITED",22.35807,114.12372,"新界葵涌光輝圍21號昌發大廈地下6號鋪","Kwai Tsing","葵青","General Restaurant","2027-05-25",[]],["fehd_2291802862","新大昌餐廳小廚","新大昌餐廳小廚",22.3621,114.12559,"新界葵涌葵盛西邨商場地下13號鋪","Kwai Tsing","葵青","General Restaurant","2026-05-26",[]],["fehd_2291802871","微笑","Olbye",22.36184,114.12907,"新界青衣青敬路51號青衣泳池地下","Kwai Tsing","葵青","General Restaurant","2027-06-01",[]],["fehd_2291802880","成都冒菜","成都冒菜",22.35862,114.12749,"新界葵涌信芳街36-42號豪勝閣地下E鋪及鋪前露天座位","Kwai Tsing","葵青","General Restaurant","2026-06-07",["Outside Seating"]],["fehd_2291802899","譚仔雲南米線","譚仔雲南米線",22.36035,114.12931,"新界青衣担杆山路6號長發邨長發商場2樓208及208A號鋪","Kwai Tsing","葵青","General Restaurant","2027-07-14",[]],["fehd_2291802905","大家樂","Cafe de Coral",22.35891,114.12213,"新界葵涌荔景山路180號賢麗苑 賢麗苑商場地下2號鋪","Kwai Tsing","葵青","General Restaurant","2026-07-20",[]],["fehd_2291802923","阿里-爸爸餐廳","ALI-BABA RESTAURANT",22.35896,114.1274,"新界葵涌葵盛東邨葵盛東邨商場地下8鋪","Kwai Tsing","葵青","General Restaurant","2026-10-02",[]],["fehd_2291802950","奕帆小廚","奕帆小廚",22.3642,114.12871,"新界葵涌光輝圍39A昌偉大廈地下28鋪","Kwai Tsing","葵青","General Restaurant","2026-12-27",[]],["fehd_2291802969","We Time Cafe","We Time Cafe",22.3622,114.12718,"新界葵涌石蔭路60號金石樓地下","Kwai Tsing","葵青","General Restaurant","2027-03-22",[]],["fehd_2291802978","大家樂","Cafe de Coral",22.36152,114.12056,"新界葵涌九龍貿易中心一樓S2鋪B部份,OS2號鋪, OS2A號鋪及OS2B號鋪B部份","Kwai Tsing","葵青","General Restaurant","2027-04-04",[]],["fehd_2291802996","楊記麻辣魚館","楊記麻辣魚館",22.35973,114.12881,"新界葵涌禾塘咀街109-115號萬成大廈地下B及C鋪","Kwai Tsing","葵青","General Restaurant","2027-04-26",[]],["fehd_2291803005","ORERYUSHIO","ORERYUSHIO",22.35702,114.12686,"新界葵涌興芳路223號新都會廣場第一層117號鋪","Kwai Tsing","葵青","General Restaurant","2027-05-04",[]],["fehd_2291803014","芽莊（葵芳）越式料理","Nha Trang (MP) Vietnamese Cuisine",22.35753,114.12324,"新界葵涌興芳路223號新都會廣場1樓133號鋪","Kwai Tsing","葵青","General Restaurant","2027-07-04",[]],["fehd_2291803023","紅茶","紅茶",22.3632,114.12685,"新界葵涌大廈街5-17號仁雅大廈地下D,E及F鋪","Kwai Tsing","葵青","General Restaurant","2026-07-20",[]],["fehd_2291803032","金林閣","KINRINKO RESTAURANT",22.36445,114.12804,"新界葵涌和宜合道 119 號香港荃灣絲麗酒店 地下 ( 部份 ) ,  1 樓 ( 部份 ) 及 2 樓 ( 部份 )","Kwai Tsing","葵青","General Restaurant","2026-07-20",["Raw Oysters","Sashimi","Sushi"]],["fehd_2291803041","MR. BURGER & CAFE","MR. BURGER & CAFE",22.36313,114.12433,"新界青衣細山路2-16號美景花園10座第三層28鋪","Kwai Tsing","葵青","General Restaurant","2026-08-10",[]],["fehd_2291803050","銀龍茶餐廳","NGAN LUNG  RESTAURANT",22.35863,114.12821,"新界青衣担杆山路6號長發邨長發廣場4樓402及403鋪","Kwai Tsing","葵青","General Restaurant","2026-08-13",[]],["fehd_2291803087","麥當勞餐廳","McDonald's Restaurant",22.36171,114.12271,"新界葵芳興芳路223號新都會廣場5樓541號鋪","Kwai Tsing","葵青","General Restaurant","2026-10-08",[]],["fehd_2291803096","三悅冰室","三悅冰室",22.35818,114.12591,"新界青衣青康路12號長康邨商場二期第一層108-110號鋪","Kwai Tsing","葵青","General Restaurant","2026-10-09",[]],["fehd_2291803111","陽光美食屋","陽光美食屋",22.36275,114.12381,"新界葵涌信芳街10-20號月波樓地下B1號鋪","Kwai Tsing","葵青","General Restaurant","2026-10-23",[]],["fehd_2291803139","好好點心飲茶椰子雞煲專門店","好好點心飲茶椰子雞煲專門店",22.36411,114.12599,"新界葵涌大隴街153號怡勝花園地下低層8-9號鋪（B部份）","Kwai Tsing","葵青","General Restaurant","2026-11-13",[]],["fehd_2291803148","樂天皇朝","Paradise Dynasty",22.36417,114.12473,"新界青衣青敬路33號青衣城第3層310B號鋪","Kwai Tsing","葵青","General Restaurant","2026-11-22",[]],["fehd_2291803166","Bugis restaurant","武吉士",22.3592,114.1233,"新界葵涌葵昌路51-53號九龍貿易中心1樓S1鋪","Kwai Tsing","葵青","General Restaurant","2026-12-17",[]],["fehd_2291803175","珍滋味","珍滋味",22.35663,114.12913,"新界青衣青衣路一號藍澄灣藍澄灣商場第一層18號鋪","Kwai Tsing","葵青","General Restaurant","2026-12-19",[]],["fehd_2291803184","和記冰室","和記冰室",22.36299,114.12861,"新界葵涌青山公路482號和記新邨 地下10,11A1,11A,11B,11C鋪","Kwai Tsing","葵青","General Restaurant","2027-01-07",[]],["fehd_2291803193","四季冰室","Seasons Cafe",22.36462,114.12854,"新界青衣長發邨街市地下146號檔","Kwai Tsing","葵青","General Restaurant","2027-01-18",[]],["fehd_2291803209","Eat@Ease","Eat@Ease",22.35556,114.12867,"新界葵涌圳邊街15-19號1樓(部份)","Kwai Tsing","葵青","General Restaurant","2027-01-25",["Raw Oysters","Sashimi","Sushi"]],["fehd_2291803218","大快活快餐","Fairwood Fast Food",22.3551,114.1281,"新界葵涌梨木道120號石蔭商場LG2 LG212鋪","Kwai Tsing","葵青","General Restaurant","2027-01-25",[]],["fehd_2291803236","香港西廚學院","Hong Kong Culinary Academy",22.36275,114.12629,"新界葵涌敬祖路6號祖堯邨祖堯商場C座一樓106-108鋪","Kwai Tsing","葵青","General Restaurant","2027-04-08",[]],["fehd_2291803245","翠園","JADE GARDEN",22.35544,114.12259,"新界葵涌興寧路12號葵青劇院地下1號鋪","Kwai Tsing","葵青","General Restaurant","2027-04-19",["Sashimi"]],["fehd_2291803272","元氣壽司","GENKI SUSHI",22.36162,114.12207,"新界葵涌興芳路223號新都會廣場第4層480-483鋪","Kwai Tsing","葵青","General Restaurant","2027-05-20",["Raw Oysters","Sashimi","Sushi"]],["fehd_2291803290","麥當勞餐廳","McDonald's Restaurant",22.36342,114.12301,"新界青衣青敬路31號青衣城地下G36-37號鋪","Kwai Tsing","葵青","General Restaurant","2027-05-27",[]],["fehd_2291803306","鰹烏冬","Katsuo Udon",22.35627,114.1287,"新界葵芳興芳路223號新都會廣場第3層329號鋪","Kwai Tsing","葵青","General Restaurant","2026-05-27",[]],["fehd_2291803324","元氣壽司","GENKI SUSHI",22.3636,114.12235,"新界青衣青敬路31號青衣城2樓228號鋪","Kwai Tsing","葵青","General Restaurant","2027-05-29",["Raw Oysters","Sashimi","Sushi"]],["fehd_2291803351","大家樂, 一粥麵及米線陣","Cafe de Coral, Super Super & Mixian Sense",22.35547,114.12282,"新界青衣青衣城地下G32-33鋪","Kwai Tsing","葵青","General Restaurant","2027-06-06",[]],["fehd_2291803379","Beans the Rambler","Beans the Rambler",22.35681,114.12208,"新界青衣青衣城第二層222號鋪","Kwai Tsing","葵青","General Restaurant","2027-06-11",["Raw Oysters","Sashimi","Sushi"]],["fehd_2291803397","Hungry Korean","Hungry Korean",22.35852,114.12467,"新界青衣青衣城2樓226號鋪","Kwai Tsing","葵青","General Restaurant","2027-06-13",[]],["fehd_2291803403","PIZZAEXPRESS","PIZZAEXPRESS",22.35534,114.12305,"新界青衣青敬路33號青衣城325號鋪","Kwai Tsing","葵青","General Restaurant","2026-06-13",[]],["fehd_2291803412","101Taiwanese Cafe","101Taiwanese Cafe",22.36335,114.12784,"新界青衣青衣城地下G30號鋪","Kwai Tsing","葵青","General Restaurant","2026-06-20",[]],["fehd_2291803430","富園海鮮酒家","RICH GARDEN RESTAURANT",22.36158,114.12799,"新界青衣牙鷹洲街8號灝景灣商場第4層","Kwai Tsing","葵青","General Restaurant","2026-07-10",[]],["fehd_2291803449","魅廚","魅廚",22.36168,114.12489,"新界葵涌和宜合道74-88號宜和樓地下84號鋪","Kwai Tsing","葵青","General Restaurant","2026-07-15",[]],["fehd_2291803458","翠苑牛雜粉麵專家","翠苑牛雜粉麵專家",22.3567,114.12268,"新界葵涌石蔭路113及117號獅子樓地下F鋪","Kwai Tsing","葵青","General Restaurant","2026-07-17",[]],["fehd_2291803476","但馬屋","Tajimaya",22.35511,114.12008,"新界葵涌興芳路223號新都會廣場第2層251-255號鋪","Kwai Tsing","葵青","General Restaurant","2026-08-27",[]],["fehd_2291803485","雲貴軒","THE VERMICELLI HOUSE",22.35534,114.12492,"新界葵涌光輝圍7-9號光輝大廈地下B鋪B2部份","Kwai Tsing","葵青","General Restaurant","2026-09-05",[]],["fehd_2291803494","雲石堡","MARBLE BOBO",22.36353,114.12689,"新界葵涌景荔徑8號盈暉薈1樓116A,136及137鋪","Kwai Tsing","葵青","General Restaurant","2026-09-06",[]],["fehd_2291803500","COZi Lounge","COZi Lounge",22.36327,114.1211,"新界葵涌青山公路-葵涌段443-451號紅A中心地下高層部份","Kwai Tsing","葵青","General Restaurant","2026-09-26",["Raw Oysters","Sashimi","Sushi"]],["fehd_2291803519","The Platter","The Platter",22.36499,114.12427,"新界葵涌青山公路-葵涌段443-451號紅A中心地下低層部份","Kwai Tsing","葵青","General Restaurant","2026-09-26",["Raw Oysters","Sashimi","Sushi"]],["fehd_2291803528","必勝客","Pizza Hut",22.36131,114.12469,"新界青衣翠怡花園商場2期地下G1號鋪","Kwai Tsing","葵青","General Restaurant","2026-10-10",[]],["fehd_2291803537","星聚軒","Star Cuisine",22.36104,114.12111,"新界葵涌葵昌路72-76號活@KCC9樓全層","Kwai Tsing","葵青","General Restaurant","2026-10-11",[]],["fehd_2291803555","爭鮮迴轉壽司","Sushi Express",22.36106,114.12972,"新界葵涌葵富路7-11號葵涌廣場3樓83號鋪及89A號鋪","Kwai Tsing","葵青","General Restaurant","2026-11-05",["Sashimi","Sushi"]],["fehd_2291803564","Mos Burger","Mos Burger",22.36398,114.12036,"新界葵涌葵昌路72-76號LIFE@KCC四樓 405-407鋪","Kwai Tsing","葵青","General Restaurant","2026-11-08",[]],["fehd_2291803573","彩匯皇宮","Choi Wui Palace",22.36491,114.12023,"新界青衣担杆山路 6 號長發邨 長發廣場 5 樓 502 號鋪","Kwai Tsing","葵青","General Restaurant","2026-11-19",[]],["fehd_2291803591","一品南餐室","Mas Viet One",22.36361,114.12603,"新界葵涌葵昌路72-76號活@KCC1樓101及103號鋪","Kwai Tsing","葵青","General Restaurant","2026-11-20",[]],["fehd_2291803607","稻成","DAB-PA",22.35904,114.12314,"新界葵涌興芳路223號新都會廣場第4層413-416號鋪","Kwai Tsing","葵青","General Restaurant","2026-11-26",[]],["fehd_2291803616","肯德基","KFC",22.36451,114.12695,"新界青衣長發邨長發廣場地下114C號鋪","Kwai Tsing","葵青","General Restaurant","2026-12-12",[]],["fehd_2291803625","南記冰室","南記冰室",22.35682,114.12507,"新界葵涌葵昌路72-76號LIFE@KCC 地下G03及G04號鋪","Kwai Tsing","葵青","General Restaurant","2026-12-17",[]],["fehd_2291803634","炑八(34)","Meokbang Korean BBQ & Bar",22.35926,114.12653,"新界青衣青敬路31-33號青衣城1樓119B舖","Kwai Tsing","葵青","General Restaurant","2026-12-20",[]],["fehd_2291803643","Green Entrance","Green Entrance",22.35627,114.12138,"新界葵涌葵昌路72-76號LIFE@KCC8樓804號鋪","Kwai Tsing","葵青","General Restaurant","2027-01-14",[]],["fehd_2291803652","SEASON CAFE","SEASON CAFE",22.35522,114.12087,"新界葵涌葵昌路72-76號活@KCC8樓801號鋪","Kwai Tsing","葵青","General Restaurant","2027-01-17",[]],["fehd_2291803670","必勝客","Pizza Hut",22.35918,114.125,"新界葵涌葵芳興芳路223號新都會廣場第2層267-269號鋪","Kwai Tsing","葵青","General Restaurant","2027-02-07",[]],["fehd_2291803704","敏華冰廳","Men Wah Bing Teng",22.35555,114.12128,"新界葵涌興芳路223號新都會廣場第1層165號鋪","Kwai Tsing","葵青","General Restaurant","2027-02-18",[]],["fehd_2291803713","泰然","Thai Yin",22.35749,114.12397,"新界青衣擔桿山路6號長發廣場地下114B號鋪","Kwai Tsing","葵青","General Restaurant","2027-02-21",["Raw Oysters","Sashimi","Sushi"]],["fehd_2291803731","吉野家","Yoshinoya",22.36095,114.12699,"新界葵涌葵昌路72-76號 活@KCC4樓401號鋪","Kwai Tsing","葵青","General Restaurant","2027-05-14",[]],["fehd_2291803740","麥當勞餐廳","McDonald's Restaurant",22.35658,114.12151,"新界青衣 楓樹窩路10號 青衣邨 青衣商場     地下S1-S2號鋪","Kwai Tsing","葵青","General Restaurant","2027-05-19",[]],["fehd_2291803759","茶木．台式休閒餐廳","Teawood Taiwanese Cafe & Restaurant",22.36409,114.12779,"新界青衣青敬路31-33號青衣城地下G07-G09號鋪","Kwai Tsing","葵青","General Restaurant","2027-05-22",[]],["fehd_2291803768","FORTUNATE COFFEE","FORTUNATE COFFEE",22.36344,114.12859,"新界葵涌葵榮路30-34號EDGE一樓7號鋪","Kwai Tsing","葵青","General Restaurant","2027-05-26",[]],["fehd_2291803777","沒有記錄","No Record",22.36486,114.1214,"新界青衣青敬路33號青衣城地下G02號鋪","Kwai Tsing","葵青","General Restaurant","2027-06-02",[]],["fehd_2291803786","友義氣‧酸菜魚","友義氣‧酸菜魚",22.35973,114.12697,"新界葵涌榮芳路9號恆景商場地下G01及G11A鋪","Kwai Tsing","葵青","General Restaurant","2026-07-02",[]],["fehd_2291803829","香港仔南記粉麵","Hong Kong Nam Kee Noodle",22.3601,114.12417,"新界青衣   青敬路33號青衣城地下G15及G16號鋪","Kwai Tsing","葵青","General Restaurant","2026-07-28",[]],["fehd_2291803865","樂園麵家","Lok Yuen Noodles Restaurant",22.36374,114.1249,"新界葵涌葵興邨葵興商場地下13-14號鋪","Kwai Tsing","葵青","General Restaurant","2026-08-08",[]],["fehd_2291803874","魚米湯加","Yu Mai Soup Plus",22.35532,114.12623,"新界青衣担杆山路6號長發邨長發商場2樓211號鋪","Kwai Tsing","葵青","General Restaurant","2026-08-14",[]],["fehd_2291803883","梨木道小鍋米線","梨木道小鍋米線",22.36056,114.12554,"新界葵涌梨木道102-116號葵寶大廈低層地下11號鋪","Kwai Tsing","葵青","General Restaurant","2026-08-19",[]],["fehd_2291803892","薩莉亞意式餐廳","SAIZERIYA ITALIAN RESTAURANT",22.35937,114.12562,"新界青衣担桿山路6號長發邨長發廣場5樓501A號鋪","Kwai Tsing","葵青","General Restaurant","2026-08-19",[]],["fehd_2291803917","朱敏記小廚","CHU MAN KEE KITCHEN",22.36105,114.12573,"新界葵涌葵涌道1001號德昌大廈地下26B及C號鋪","Kwai Tsing","葵青","General Restaurant","2026-09-08",[]],["fehd_2291803926","大家樂","Cafe De Coral",22.35952,114.12595,"新界葵涌貨櫃碼頭路77-81號大鴻輝(葵涌)中心 地下7, 8及9號鋪","Kwai Tsing","葵青","General Restaurant","2026-09-23",[]],["fehd_2291803935","客滿庭","Hakka Cuisine",22.36163,114.12946,"新界葵涌興芳路177號葵芳邨商業/停車場(葵芳廣場) 一樓116及116A號鋪","Kwai Tsing","葵青","General Restaurant","2026-11-26",[]],["fehd_2291803944","明越","MINH VIET",22.35592,114.12659,"新界青衣翠怡商場一期地下4號鋪","Kwai Tsing","葵青","General Restaurant","2027-01-16",[]],["fehd_2291803953","海港燒鵝海鮮酒家","VICTORIA HARBOUR ROASTED GOOSE SEAFOOD RESTAURANT",22.35573,114.12095,"新界葵涌興芳路177號葵芳廣場地下17號鋪","Kwai Tsing","葵青","General Restaurant","2027-02-13",["Sashimi"]],["fehd_2291803980","霸王餐室","霸王餐室",22.36462,114.12435,"新界葵涌打磚坪街1-25號，和宜合道5-27號 寶星廣場(1樓75,76,77號鋪除外)小部份","Kwai Tsing","葵青","General Restaurant","2027-03-04",[]],["fehd_2291803999","大快活快餐","Fairwood Fast Food",22.35973,114.12844,"新界青衣青康路12號長康邨康和樓地下1,2,3,4號鋪","Kwai Tsing","葵青","General Restaurant","2027-03-10",[]],["fehd_2291804035","瑩瑩工房","瑩瑩工房",22.36208,114.12917,"新界青衣長青邨街市1樓1號鋪","Kwai Tsing","葵青","General Restaurant","2027-04-16",[]],["fehd_2291804044","金百滬小籠包專門店","JIN BAI HU",22.36223,114.12675,"新界青衣担杆山路6號長發邨長發廣場5樓501C及501D號鋪","Kwai Tsing","葵青","General Restaurant","2027-04-27",[]],["fehd_2291804053","巴打冰室","BUDDY CAFE",22.36055,114.1253,"新界葵涌石蔭路44號金石樓地下8號鋪","Kwai Tsing","葵青","General Restaurant","2027-04-27",[]],["fehd_2291804071","集成","CHAP SHING",22.36009,114.12873,"新界葵涌大窩口道15號大窩口邨商業/停車場大樓 (又稱大窩口商業中心1座)2樓C15號","Kwai Tsing","葵青","General Restaurant","2027-04-29",[]],["fehd_2291804099","好味餃子店","Delicious Dumpling Shop",22.36062,114.12464,"新界葵涌禮芳街5-23號葵福大廈地下8號室","Kwai Tsing","葵青","General Restaurant","2027-04-30",[]],["fehd_2291804105","你好！茶飯","HiYa! ChaFan",22.35791,114.12957,"新界葵涌興芳路177號葵芳邨商業/停車場 (葵芳廣場)地下3號鋪","Kwai Tsing","葵青","General Restaurant","2027-05-21",[]],["fehd_2291804114","三悅冰室","三悅冰室",22.36041,114.1267,"新界葵涌興芳路177號葵芳邨葵芳廣場地下2號鋪","Kwai Tsing","葵青","General Restaurant","2026-05-26",[]],["fehd_2291804123","百份百 & 意樂","CAFE 100% & Itamomo",22.35792,114.12267,"新界葵涌石籬邨石籬商場2期3樓324號鋪(A部份)","Kwai Tsing","葵青","General Restaurant","2027-06-02",[]],["fehd_2291804132","Jungle Grill","Jungle Grill",22.36448,114.12997,"新界葵涌興芳路177號葵芳廣場地下18號鋪","Kwai Tsing","葵青","General Restaurant","2026-06-03",[]],["fehd_2291804141","小幸冰室","Lucky Cafe",22.35938,114.12388,"新界葵涌大白田街19-31號安盛大廈地下29號鋪","Kwai Tsing","葵青","General Restaurant","2027-06-11",[]],["fehd_2291804150","中心點","Meet Point",22.36203,114.12413,"新界青衣青康路12號長康邨長康商業中心二期地下 104及105號鋪","Kwai Tsing","葵青","General Restaurant","2026-07-02",[]],["fehd_2291804178","新潮興牛雜粉店","Chiu Hing Noodle Shop",22.3596,114.12905,"新界葵涌興芳路204號葵芳匯地下G05A號鋪","Kwai Tsing","葵青","General Restaurant","2026-08-16",[]],["fehd_2291804196","珍寶美食","珍寶美食",22.35789,114.12185,"新界葵涌葵興路100-102號 葵涌中心地下A11鋪","Kwai Tsing","葵青","General Restaurant","2026-08-11",[]],["fehd_2291804211","大榕樹下","大榕樹下",22.3563,114.12947,"新界青衣青敬路33號青衣城地下G01號舖","Kwai Tsing","葵青","General Restaurant","2026-09-17",[]],["fehd_2291804239","檸檬冰室","Lemon Cafe",22.35524,114.12171,"新界葵涌禾葵里2號葵興邨興國樓1座地下10-12號鋪","Kwai Tsing","葵青","General Restaurant","2026-10-08",[]],["fehd_2291804257","茶樂冰廳","茶樂冰廳",22.35871,114.12338,"新界葵涌石蔭路93, 95 及97號光輝樓地下C, D及E號 鋪","Kwai Tsing","葵青","General Restaurant","2026-11-08",[]],["fehd_2291804266","譚仔三哥米線","譚仔三哥米線",22.36184,114.12173,"新界葵涌葵富路7-11號葵涌廣場1樓B93號鋪","Kwai Tsing","葵青","General Restaurant","2026-11-09",[]],["fehd_2291804275","OK 冰室","OK 冰室",22.36047,114.12455,"新界葵涌葵昌路51號九龍貿易中心二樓213號鋪","Kwai Tsing","葵青","General Restaurant","2026-11-11",[]],["fehd_2291804309","譚仔三哥米線","譚仔三哥米線",22.36146,114.12001,"新界葵涌圍乪街6號石籬邨 石籬商場(一期)1樓A108號鋪","Kwai Tsing","葵青","General Restaurant","2026-12-29",[]],["fehd_2291804318","駱腳點","駱腳點",22.36005,114.12658,"新界葵涌興芳路177號葵芳邨商業/停車場大樓 (葵芳廣場)地下1號鋪","Kwai Tsing","葵青","General Restaurant","2027-01-10",[]],["fehd_2291804327","薩莉亞意式餐廳","SAIZERIYA ITALIAN RESTAURANT",22.35902,114.12505,"新界葵涌新葵興廣場3樓2號鋪","Kwai Tsing","葵青","General Restaurant","2027-01-25",[]],["fehd_2291804336","爭鮮迴轉壽司","SUSHI EXPRESS",22.35834,114.12342,"新界葵涌大隴街110號石籬邨石籬商場二期3樓B318鋪","Kwai Tsing","葵青","General Restaurant","2027-01-27",["Sashimi","Sushi"]],["fehd_2291804345","魚米, 湯加, 春月堂","Yu Mai, Soup Plus, Moon Cafe",22.357,114.12787,"新界葵涌大隴街110號石籬邨石籬商埸2期(商埸/停車場大樓) 2樓B232A號鋪","Kwai Tsing","葵青","General Restaurant","2027-02-22",[]],["fehd_2291804354","大家樂","Cafe de Coral",22.35979,114.12958,"新界葵涌大窩口道15號大窩口邨大窩口商場(I)期 1樓B05號鋪","Kwai Tsing","葵青","General Restaurant","2027-03-01",[]],["fehd_2291804363","大頭蝦東南亞餐廳","KING PRAWN ASIAN RESTAURANT",22.36324,114.12167,"新界葵涌   新葵興廣場 3樓 9-10號鋪","Kwai Tsing","葵青","General Restaurant","2027-03-08",[]],["fehd_2291804372","阿里山鐵路便當","ALISHAN FOOD STATION",22.35866,114.12042,"新界青衣第111號地段的餘段翠怡花園翠怡商場第一期地下6號鋪","Kwai Tsing","葵青","General Restaurant","2027-03-16",[]],["fehd_2291804381","金港冰室","金港冰室",22.35549,114.12917,"新界葵涌葵涌道1013-1033號昌年大廈地下A號鋪","Kwai Tsing","葵青","General Restaurant","2027-04-21",[]],["fehd_2291804390","燒鵝大亨茶餐廳","燒鵝大亨茶餐廳",22.3589,114.12152,"新界葵涌大窩口道15號大窩口邨大窩口商場(I)期 1樓B03 及 B04號鋪","Kwai Tsing","葵青","General Restaurant","2027-04-22",[]],["fehd_2291804406","大家樂","Cafe de Coral",22.36475,114.12568,"新界葵涌大隴街110號石籬邨石籬商場二期1樓B111鋪","Kwai Tsing","葵青","General Restaurant","2027-04-27",[]],["fehd_2291804415","香港仔冰室","Aberdeen Cafe",22.35959,114.12055,"新界葵涌   新葵興廣場 3樓11號鋪","Kwai Tsing","葵青","General Restaurant","2027-05-16",[]],["fehd_2291804424","譚仔三哥米線","譚仔三哥米線",22.36445,114.12115,"新界青衣 青敬路31號  青衣城 1樓180號鋪","Kwai Tsing","葵青","General Restaurant","2027-05-31",[]],["fehd_2291804433","鷹將軍冰室","鷹將軍冰室",22.35945,114.12378,"新界葵涌葵昌路51號九龍貿易中心2樓閣樓M04鋪","Kwai Tsing","葵青","General Restaurant","2027-06-06",[]],["fehd_2291804442","太子粉麵","太子粉麵",22.35769,114.12591,"新界青衣寮肚路6號長亨邨商業/停車場 (又稱長亨商場)街市地下 (前稱地下低層4樓)37,38及39號檔","Kwai Tsing","葵青","General Restaurant","2027-06-15",[]],["fehd_2291804451","永樂燒味廚房","WING LOK ROAST KITCHEN",22.3568,114.12895,"新界葵涌禮芳街5號葵福大廈地下11號鋪","Kwai Tsing","葵青","General Restaurant","2026-06-29",[]],["fehd_2291804460","百滙酒家","DELUXE RESTAURANT",22.36349,114.12486,"新界葵涌大隴街110號石籬邨石籬商場2期2樓 B210, B211及 B212號鋪","Kwai Tsing","葵青","General Restaurant","2027-07-04",[]],["fehd_2291804488","星慧小館","星慧小館",22.35848,114.12634,"新界葵涌大窩口道15號大窩口邨大窩口商場(I)期 2樓C02A, C02, C03及C04鋪","Kwai Tsing","葵青","General Restaurant","2026-08-02",[]],["fehd_2291804497","百份百餐廳","Cafe 100%",22.35649,114.12094,"新界青衣長亨邨長亨商場3樓319-320號鋪","Kwai Tsing","葵青","General Restaurant","2026-09-16",[]],["fehd_2291804549","必勝客","Pizza Hut",22.35759,114.12441,"新界青衣 寮肚路6號  長亨商場 3樓 317-318號鋪","Kwai Tsing","葵青","General Restaurant","2026-10-10",[]],["fehd_2291804558","波士餃子","波士餃子",22.36328,114.12841,"新界葵涌大隴街113/117及121/127號昌盛樓 地下4號鋪","Kwai Tsing","葵青","General Restaurant","2026-10-14",[]],["fehd_2291804567","麥當勞餐廳","McDonald's Restaurant",22.35585,114.12838,"新界葵涌大隴街110號石籬邨 石籬商場二期地下B013-B016號鋪","Kwai Tsing","葵青","General Restaurant","2026-10-24",[]],["fehd_2291804576","花莉廚房","FINALLY OUR KITCHEN",22.35746,114.12654,"新界青衣涌美道涌美老屋村136號地下(部份)","Kwai Tsing","葵青","General Restaurant","2026-11-16",["Sashimi","Sushi"]],["fehd_2291804585","元氣壽司","Genki Sushi",22.36232,114.12475,"新界葵涌葵義路2-10號 好爵中心43號鋪(部份)及地下44-48號鋪","Kwai Tsing","葵青","General Restaurant","2026-12-01",["Raw Oysters","Sashimi","Sushi"]],["fehd_2291804594","Yakiniku Like","Yakiniku Like",22.36231,114.12375,"新界葵涌興芳路223號新都會廣場 第1層 112號鋪","Kwai Tsing","葵青","General Restaurant","2026-12-12",[]],["fehd_2291804600","惠比壽本店","EBISU JAPANESE RESTAURANT",22.35521,114.12734,"新界葵涌興芳路204號葵芳滙1樓101室","Kwai Tsing","葵青","General Restaurant","2026-12-28",["Sashimi","Sushi"]],["fehd_2291804628","泰潮","THAI CHIU",22.35652,114.12119,"新界葵涌興芳路223號新都會廣場第一層167號鋪","Kwai Tsing","葵青","General Restaurant","2027-01-17",[]],["fehd_2291804637","譚仔三哥米線","譚仔三哥米線",22.36012,114.12588,"新界青衣 青康路12號  長康邨商場一期 康貴樓 地下2-4鋪","Kwai Tsing","葵青","General Restaurant","2027-01-18",[]],["fehd_2291804655","薩莉亞意式餐廳","SAIZERIYA ITALIAN RESTAURANT",22.36038,114.12835,"新界青衣美景花園商場第三層49-54號鋪","Kwai Tsing","葵青","General Restaurant","2027-02-13",[]],["fehd_2291804664","一鍋堂","E POT",22.3572,114.12091,"新界葵涌葵芳興芳路223號新都會廣場 六樓601至610號鋪","Kwai Tsing","葵青","General Restaurant","2027-02-14",["Sashimi","Sushi"]],["fehd_2291804673","金島快餐","金島快餐",22.36026,114.12983,"新界青衣美景花園 第5座地下84-86號鋪","Kwai Tsing","葵青","General Restaurant","2027-02-09",[]],["fehd_2291804691","四季燒臘家","Four Seasons Roast Meat",22.35666,114.12494,"新界葵涌石籬一邨石籬商場地下14號檔","Kwai Tsing","葵青","General Restaurant","2027-02-17",[]],["fehd_2291804707","新金豐餐廳","NEW KAM FUNG RESTAURANT",22.36473,114.12706,"新界葵涌石蔭路113-117號地下A-C鋪","Kwai Tsing","葵青","General Restaurant","2027-02-17",[]],["fehd_2291804716","源興燒味小館","源興燒味小館",22.36399,114.12685,"新界葵涌禾塘咀街109-115號地下A號鋪","Kwai Tsing","葵青","General Restaurant","2027-03-17",[]],["fehd_2291804725","幸運星","Lucky Star",22.36223,114.12031,"新界葵涌青山公路501/503及507/511號 友成大樓地下B號鋪","Kwai Tsing","葵青","General Restaurant","2027-03-20",[]],["fehd_2291804734","銀龍茶餐廳","Ngan Lung Restaurant",22.36172,114.12621,"新界葵涌  葵盛東邨 葵盛東商場 1樓 106A鋪","Kwai Tsing","葵青","General Restaurant","2027-03-20",[]],["fehd_2291804752","壽司郎葵芳店","Sushiro Kwai Fong",22.363,114.12395,"新界葵芳興芳路223號新都會廣場1樓176-177號鋪","Kwai Tsing","葵青","General Restaurant","2027-03-24",["Sashimi","Sushi"]],["fehd_2291804761","堅信號上海生煎皇","GING SUN HO KING OF BUN",22.36229,114.12269,"新界青衣青敬路31號青衣城1樓197號鋪","Kwai Tsing","葵青","General Restaurant","2027-04-07",[]],["fehd_2291804770","亞參雞飯","Asam Chicken Rice",22.36156,114.12548,"新界青衣青敬路33號青衣城第二層218A號鋪","Kwai Tsing","葵青","General Restaurant","2027-04-13",[]],["fehd_2291804789","譚仔三哥米線","譚仔三哥米線",22.36095,114.12927,"新界葵涌  葵盛東邨 葵盛東商場 地下6A號鋪","Kwai Tsing","葵青","General Restaurant","2027-05-10",[]],["fehd_2291804798","8鍋臭臭鍋","8鍋臭臭鍋",22.36199,114.12283,"新界葵涌興芳路208號葵芳匯2樓201號鋪","Kwai Tsing","葵青","General Restaurant","2027-05-15",[]],["fehd_2291804804","春水堂","Chun Shui Tang",22.36469,114.12712,"新界葵涌興芳路223號新都會廣場第4層410-412號鋪","Kwai Tsing","葵青","General Restaurant","2027-05-30",[]],["fehd_2291804822","豪華茶餐廳","豪華茶餐廳",22.35763,114.12126,"新界葵涌 屏富徑14號及16號(主要部份)地下","Kwai Tsing","葵青","General Restaurant","2027-06-05",[]],["fehd_2291804831","一粥麵","SUPER SUPER",22.35855,114.12331,"新界青衣細山路2-16號美景花園3樓40-41 & 59-60 & 70-71號鋪","Kwai Tsing","葵青","General Restaurant","2027-06-13",[]],["fehd_2291804840","茶泰","Cha Thai",22.35905,114.12531,"新界葵芳興芳路223號新都會廣場5樓501-510號鋪","Kwai Tsing","葵青","General Restaurant","2027-06-14",[]],["fehd_2291804859","銀龍冰室","Ngan Lung Cafe",22.35806,114.12897,"新界葵涌大隴街110號石籬邨 石籬商場二期地下B004及B005號鋪主要部份","Kwai Tsing","葵青","General Restaurant","2026-06-16",[]],["fehd_2291804868","十二味","十二味",22.35792,114.12405,"新界青衣青敬路31號青衣城2樓224號鋪","Kwai Tsing","葵青","General Restaurant","2026-06-28",[]],["fehd_2291804886","大快活快餐","Fairwood Fast Food",22.36083,114.12662,"新界葵涌葵盛東邨葵盛東商場地下3及4鋪","Kwai Tsing","葵青","General Restaurant","2027-07-03",[]],["fehd_2291804895","翠河燒味","翠河燒味",22.35823,114.12443,"新界葵涌石蔭邨石蔭商埸LG1樓110鋪","Kwai Tsing","葵青","General Restaurant","2026-07-14",[]],["fehd_2291804901","百芳池上便當","百芳池上便當",22.35599,114.12096,"新界葵涌葵昌路72-76號活@KCC1樓108號鋪","Kwai Tsing","葵青","General Restaurant","2026-07-17",[]],["fehd_2291804910","山西刀削麵皇","SHANXI NOODLE KING",22.35832,114.12964,"新界葵涌信芳街24號至28號地下3及4號鋪","Kwai Tsing","葵青","General Restaurant","2026-07-26",[]],["fehd_2291804929","冠記美食","冠記美食",22.3591,114.12148,"新界葵涌和宜合道182-184號瑞景大廈地下1至2號鋪","Kwai Tsing","葵青","General Restaurant","2026-08-01",[]],["fehd_2291804938","牛奶冰室","MILK CAFE",22.36277,114.12155,"新界青衣細山路2-16號美景花園3樓55-58號鋪","Kwai Tsing","葵青","General Restaurant","2026-09-25",[]],["fehd_2291804947","CHICKEN FACTORY","CHICKEN FACTORY",22.3646,114.12871,"新界青衣細山路2-16號美景花園第三層36號鋪","Kwai Tsing","葵青","General Restaurant","2026-11-02",[]],["fehd_2291804956","大快活快餐","Fairwood Fast Food",22.35681,114.1216,"新界青衣青綠街7-19號青怡花園青怡商場1樓4-8號鋪","Kwai Tsing","葵青","General Restaurant","2026-11-23",[]],["fehd_2291804965","荷蘭冰室","荷蘭冰室",22.36303,114.12927,"新界葵涌葵盛東邨葵盛東商場地下2及2A號鋪","Kwai Tsing","葵青","General Restaurant","2026-11-24",[]],["fehd_2291804974","牛角日本燒肉專門店","Gyukaku Japanese Yakiniku Restaurant",22.36036,114.12301,"新界葵芳興芳路223號新都會廣場6樓 611-620號鋪","Kwai Tsing","葵青","General Restaurant","2026-12-06",[]],["fehd_2291804983","譚仔雲南米線","譚仔雲南米線",22.35766,114.12029,"新界葵涌新葵興廣場3樓1號鋪A部分","Kwai Tsing","葵青","General Restaurant","2026-12-22",[]],["fehd_2291805001","燈籠滷味","LANTERN LOMEI",22.36145,114.12189,"新界葵涌葵涌市地段395號 新都會廣場1樓181號鋪","Kwai Tsing","葵青","General Restaurant","2027-01-12",[]],["fehd_2291805010","大家樂","Café de Coral",22.36307,114.12023,"新界葵涌葵涌市地段第395號 新都會廣場第2層260-265號舖","Kwai Tsing","葵青","General Restaurant","2027-01-12",[]],["fehd_2291805029","一樂冰室","Cafe De Papa",22.35898,114.12452,"新界葵涌安足街7號安蔭邨安蔭商埸地下2號鋪","Kwai Tsing","葵青","General Restaurant","2027-01-12",[]],["fehd_2291805047","茶皇殿 / 圓香","JASMINE CUISINE / PEARL CASTLE",22.36103,114.12972,"新界葵涌上角街葵涌商場207號鋪1字樓 (部份)及地下(部份)","Kwai Tsing","葵青","General Restaurant","2027-03-21",[]],["fehd_2291805056","輝記粥品","輝記粥品",22.36073,114.1288,"新界葵涌禮芳街5-23號葵福大廈地下 4號鋪","Kwai Tsing","葵青","General Restaurant","2027-03-27",[]],["fehd_2291805065","和記小廚","和記小廚",22.35703,114.12689,"新界葵涌美芳街2-14號昌鴻大廈地下6號鋪","Kwai Tsing","葵青","General Restaurant","2027-04-13",[]],["fehd_2291805074","泰作","Twinkle Elephant",22.36484,114.12071,"新界青衣青敬路33號青衣城3樓302鋪","Kwai Tsing","葵青","General Restaurant","2027-04-17",["Sashimi"]],["fehd_2291805092","大師傅粥品","大師傅粥品",22.36163,114.12921,"新界葵涌興芳路177號葵芳邨葵健樓地下3&11號鋪","Kwai Tsing","葵青","General Restaurant","2027-05-08",[]],["fehd_2291805117","道日本料理","道日本料理",22.35554,114.12264,"新界荃灣大窩口道1-9號大廈街1號及德士古道57-65號 宏華大廈地下B鋪","Kwai Tsing","葵青","General Restaurant","2026-05-23",["Sashimi","Sushi"]],["fehd_2291805126","Sutadonya","Sutadonya",22.35536,114.12152,"新界葵涌興芳路 223 號新都會廣場 第 2 層 240-243 號舖","Kwai Tsing","葵青","General Restaurant","2027-06-08",[]],["fehd_2291805135","茶豆冰室","茶豆冰室",22.35763,114.12939,"新界青衣担杆山路6號長發邨長發廣場 長發街市地下147號鋪","Kwai Tsing","葵青","General Restaurant","2027-06-12",[]],["fehd_2291805144","12燒","12燒",22.35955,114.12647,"新界葵涌興芳路177號葵芳邨葵芳廣場地下14鋪","Kwai Tsing","葵青","General Restaurant","2026-07-20",[]],["fehd_2291805153","百匯酒家","DELUXE RESTAURANT",22.35762,114.12342,"新界葵涌葵盛東邨葵盛東商場1樓129號鋪","Kwai Tsing","葵青","General Restaurant","2026-07-27",[]],["fehd_2291805162","必勝客","Pizza Hut",22.36159,114.12597,"新界葵涌 葵盛圍63號  葵盛東商場 1樓107鋪","Kwai Tsing","葵青","General Restaurant","2026-09-25",[]],["fehd_2291805171","魚眾不同","魚眾不同",22.35886,114.1269,"新界青衣担杆山路6號長發邨長發廣場3樓317號鋪","Kwai Tsing","葵青","General Restaurant","2026-09-25",[]],["fehd_2291805180","食得喜靚粥","食得喜靚粥",22.35868,114.12431,"新界葵涌安足街7號安蔭邨安蔭商埸地下9-13 及 15-19號舖一斗農林水產(安蔭)M22號檔位","Kwai Tsing","葵青","General Restaurant","2026-10-09",[]],["fehd_2291805199","吉豚屋葵涌廣場","CA-TU-YA KWAI CHUNG PLAZA",22.36415,114.12018,"新界葵涌葵富路7-11號葵涌廣場3樓(第5層) TRENDY PLACE 88B號鋪","Kwai Tsing","葵青","General Restaurant","2026-10-26",[]],["fehd_2291805223","星河宴會廳","Galaxy Banquet Hall",22.36414,114.12491,"新界葵涌景荔徑8號盈暉薈1樓126號鋪","Kwai Tsing","葵青","General Restaurant","2026-11-29",[]],["fehd_2291805232","超人燒鵝","超人燒鵝",22.35519,114.12359,"新界葵涌石蔭路78-96號天安樓地下3號舖","Kwai Tsing","葵青","General Restaurant","2027-01-11",[]],["fehd_2291805250","吉野家","Yoshinoya",22.35572,114.12896,"新界葵涌大隴街110號石籬邨石籬商場二期2樓 B201舖","Kwai Tsing","葵青","General Restaurant","2027-01-22",[]],["fehd_2291805278","烤烤食","烤烤食",22.35684,114.12356,"新界葵涌石蔭路135-147號葵寶大廈地下6A & 12A鋪","Kwai Tsing","葵青","General Restaurant","2027-01-25",[]],["fehd_2291805287","佳記冰室","佳記冰室",22.35883,114.12484,"新界葵涌葵富路7-11號 葵涌廣場地下A35, A36, A37號舖","Kwai Tsing","葵青","General Restaurant","2027-02-08",[]],["fehd_2291805311","Itamomo","Itamomo",22.36312,114.12608,"新界青衣青富苑青富商場高層地下101號鋪","Kwai Tsing","葵青","General Restaurant","2027-03-05",[]],["fehd_2291805320","牛奶冰室","Milk Cafe",22.36441,114.1295,"新界葵涌新葵興廣場3樓4號鋪","Kwai Tsing","葵青","General Restaurant","2027-03-13",[]],["fehd_2291805339","宴食堂","EN-SHOKUDO",22.35533,114.12627,"新界葵涌興芳路223號新都會廣場第1層107-108號鋪","Kwai Tsing","葵青","General Restaurant","2027-03-19",["Sashimi","Sushi"]],["fehd_2291805348","越旺越式牛肉粉海南雞專門店","越旺越式牛肉粉海南雞專門店",22.35528,114.12607,"新界葵涌石蔭路29-35及39-45號葵麗大廈地下F舗","Kwai Tsing","葵青","General Restaurant","2027-03-19",[]],["fehd_2291805357","玖子茶","玖子茶",22.36014,114.126,"新界青衣担杆山路6號長發邨長發廣場2樓213及215鋪","Kwai Tsing","葵青","General Restaurant","2027-04-02",[]],["fehd_2291805366","魚眾不同","魚眾不同",22.35872,114.12803,"新界葵涌大隴街129-137及141-151號 葵都大廈地下6號舖","Kwai Tsing","葵青","General Restaurant","2027-04-10",[]],["fehd_2291805375","大快活快餐","Fairwood Fast Food",22.35787,114.12412,"新界葵涌安足街7號安蔭邨 安蔭商場商業及停車場一樓109-111號鋪","Kwai Tsing","葵青","General Restaurant","2027-04-22",[]],["fehd_2291805384","CHICKEN POCHA","CHICKEN POCHA",22.36109,114.12761,"新界葵涌青山道438-442號名德大廈地下IA鋪及鋪前露天座","Kwai Tsing","葵青","General Restaurant","2027-05-06",["Outside Seating"]],["fehd_2291805393","昇星餐室","Rising Star Restaurant",22.35911,114.12279,"新界葵涌大窩口 大窩口邨商場1期(大窩口街市)  1樓 25-26號檔","Kwai Tsing","葵青","General Restaurant","2027-05-08",[]],["fehd_2291805409","荷里活冰室","荷里活冰室",22.35829,114.12671,"新界青衣楓樹窩路10號青衣邨青衣商場地下S6-7號舗","Kwai Tsing","葵青","General Restaurant","2027-06-06",[]],["fehd_2291805418","CANADIAN PIZZA","CANADIAN PIZZA",22.36438,114.12926,"新界葵涌大窩口道15號大窩口邨富碧樓1樓211號鋪","Kwai Tsing","葵青","General Restaurant","2026-06-11",[]],["fehd_2291805427","海悅 (青衣)","OCEAN PALACE (TSING YI)",22.36116,114.12926,"新界青衣寮肚路6號長亨邨長亨商場5樓512號鋪","Kwai Tsing","葵青","General Restaurant","2026-06-18",[]],["fehd_2291805436","雲米家","雲米家",22.36404,114.12216,"新界葵涌青山公路438-442號名德大廈地下HA鋪","Kwai Tsing","葵青","General Restaurant","2026-06-19",[]],["fehd_2291805445","小雨天/銅千斤車仔麵","小雨天/銅千斤車仔麵",22.36049,114.12673,"新界葵涌和宜合道58-64號恭誠樓地下B鋪","Kwai Tsing","葵青","General Restaurant","2026-07-17",[]],["fehd_2291805454","三點三冰室","3.3 CAFE",22.35943,114.12708,"新界青衣青敬路33號青衣城地下G24及G25號鋪","Kwai Tsing","葵青","General Restaurant","2026-07-30",[]],["fehd_2291805463","薩莉亞意式餐廳","Saizeriya Italian Restaurant",22.36404,114.12841,"新界葵青葵涌  石籬邨 石籬商場(二期) 2樓 B206 及 B207號鋪","Kwai Tsing","葵青","General Restaurant","2026-09-09",[]],["fehd_2291805472","YAPPARI STEAK","YAPPARI STEAK",22.36418,114.12347,"新界葵涌葵涌市地段第395號 新都會廣場第5層574A號鋪","Kwai Tsing","葵青","General Restaurant","2026-10-02",[]],["fehd_2291805490","泰甜","Thai & Dessert Cafe",22.35699,114.12177,"新界青衣青康路12號長康邨康貴樓(組成綜合商業/停車場的部份 位置, 康和樓和康貴樓) 地下8及9號鋪","Kwai Tsing","葵青","General Restaurant","2026-10-28",[]],["fehd_2291805506","山見台式火鍋","Sankinn Taiwanese Hot Pot",22.36165,114.1239,"新界葵涌興芳路223號新都會廣場第4層484-487號鋪","Kwai Tsing","葵青","General Restaurant","2026-11-10",["Sashimi","Sushi"]],["fehd_2291805515","熟客 X 薈欣 . 越南","SUKA X VIETMIAM",22.36426,114.12677,"新界青衣青敬路33號青衣城第二層202-203號舖","Kwai Tsing","葵青","General Restaurant","2026-11-25",["Sashimi"]],["fehd_2291805524","傳承麵家","傳承麵家",22.35972,114.12973,"新界葵涌青山道438-442號名德大廈地下IB及IC鋪","Kwai Tsing","葵青","General Restaurant","2026-12-03",[]],["fehd_2291805533","QUE 及 豚勝","QUE and TSUKANTO",22.35598,114.12193,"新界葵涌興芳路223號新都會廣場第5層547-565號鋪","Kwai Tsing","葵青","General Restaurant","2026-12-11",["Raw Meat","Raw Oysters","Sashimi","Sushi"]],["fehd_2291805542","Sukiya","Sukiya",22.35511,114.12674,"新界青衣青敬路33號青衣城一期三樓301A號鋪","Kwai Tsing","葵青","General Restaurant","2027-02-18",[]],["fehd_2291805551","壽司郎(青衣城1)","SUSHIRO (MARITIME SQUARE 1)",22.36369,114.12585,"新界青衣青敬路33號青衣城一期2樓211鋪","Kwai Tsing","葵青","General Restaurant","2027-03-16",["Sashimi","Sushi"]],["fehd_2291805560","Yakiniku Like","Yakiniku Like",22.36385,114.12819,"新界青衣 青敬路33號  青衣城 2樓212號舖","Kwai Tsing","葵青","General Restaurant","2027-03-23",[]],["fehd_2291805579","The Pantry Cafe","The Pantry Cafe",22.35946,114.12051,"新界葵涌興芳路223號新都會廣場第5層531-540號鋪","Kwai Tsing","葵青","General Restaurant","2027-03-26",[]],["fehd_2291805597","UURO","UURO",22.36111,114.12037,"新界青衣青敬路33號青衣城地下G22-G23號鋪","Kwai Tsing","葵青","General Restaurant","2027-05-25",[]],["fehd_2291805603","雞少雞飯","YOUNG CHICK & RICE",22.36047,114.12637,"新界葵涌圍乪街6號石籬邨石籬商場(一期)1樓A109號鋪","Kwai Tsing","葵青","General Restaurant","2026-05-27",[]],["fehd_2291805612","OK冰室","OK冰室",22.35526,114.12134,"新界葵涌 榮芳路9號 恒景花園 恒景商場 地下G02A & G13號鋪","Kwai Tsing","葵青","General Restaurant","2027-06-10",[]],["fehd_2291805621","老港冰室","OLD HONG KONG CAFE",22.35964,114.12968,"新界葵涌興芳路223號新都會廣場第1層109號鋪","Kwai Tsing","葵青","General Restaurant","2026-07-20",[]],["fehd_2291805630","晴天點心小廚","晴天點心小廚",22.36212,114.1244,"新界葵涌安足街7號安蔭邨安蔭商埸地下 7及8號舖","Kwai Tsing","葵青","General Restaurant","2026-08-18",[]],["fehd_2291805658","Tonkichi","Tonkichi",22.36442,114.12539,"新界青衣青敬路31-33號青衣城第一期二樓212A鋪","Kwai Tsing","葵青","General Restaurant","2026-09-18",["Raw Oysters","Sashimi","Sushi"]],["fehd_2291805667","丸龜製麵","Marugame",22.35894,114.12885,"新界葵青青衣 青敬路31號  青衣城2期 2樓 225號鋪","Kwai Tsing","葵青","General Restaurant","2026-09-21",[]],["fehd_2291805676","沙嗲王","SATAY KING",22.35751,114.12731,"新界葵涌 興芳路223號  新都會廣場 第三層 345A號鋪","Kwai Tsing","葵青","General Restaurant","2026-12-23",[]],["fehd_2291805685","興盛小館","HING SHING RESTAURANT",22.35506,114.12308,"新界葵青葵涌 葵興路100號  葵涌中心 地下A5,30,31及32號鋪","Kwai Tsing","葵青","General Restaurant","2027-01-25",[]],["fehd_2291805694","肉肉大米","NIKU NIKU OH!! KOME",22.3578,114.12704,"新界葵涌興芳路223號新都會廣場2樓272-274號舖","Kwai Tsing","葵青","General Restaurant","2027-01-27",[]],["fehd_2291805719","大西洋火鍋","ATLANTIC HOT POT",22.35734,114.12452,"新界葵青葵芳興芳路208號葵芳匯2樓202號鋪","Kwai Tsing","葵青","General Restaurant","2027-03-19",[]],["fehd_2291805728","港興粥品","港興粥品",22.36053,114.12173,"新界青衣翠怡花園第二期商場地下G16號鋪","Kwai Tsing","葵青","General Restaurant","2027-05-03",[]],["fehd_3891805671","港茶冰室","港茶冰室",22.35916,114.12917,"新界葵青葵涌 信芳街35-37號禮芳街5-13及 17-23號  葵福大廈 地下9及10號鋪","Kwai Tsing","葵青","General Restaurant","2026-05-24",[]],["fehd_3891805680","一人一鍋/ 千両","SHABU SHABU LE-TA-SU/ SEN-RYO",22.35646,114.12485,"新界青衣 青敬路33號  青衣城 3樓322B號舖","Kwai Tsing","葵青","General Restaurant","2026-06-11",["Sashimi","Sushi"]],["fehd_3891805699","金屋泰國菜館","Golden Home Thai Food",22.36103,114.12712,"新界葵涌榮芳路99-101號葵祥大廈地下及閣樓A鋪及B鋪","Kwai Tsing","葵青","General Restaurant","2026-06-11",[]],["fehd_3891805705","66冰室","66 TEA HOUSE",22.35736,114.12041,"新界葵涌葵義路2-10號好爵中心地下39-42鋪","Kwai Tsing","葵青","General Restaurant","2026-06-18",[]],["fehd_3891805714","鑽石茶餐廳","鑽石茶餐廳",22.35855,114.12575,"新界葵青青衣長青邨商場地下S15號鋪及閣樓","Kwai Tsing","葵青","General Restaurant","2026-07-07",[]],["fehd_3191000020","海景餐廳","海景餐廳",22.35763,114.12911,"新界葵涌荔景邨 日景樓10號鋪","Kwai Tsing","葵青","Light Refreshment","2026-06-30",[]],["fehd_3191000039","新香冰室","新香冰室",22.35871,114.12965,"新界葵涌 石蔭路58號地下","Kwai Tsing","葵青","Light Refreshment","2026-06-30",[]],["fehd_3191000066","俊記麵家","俊記麵家",22.35548,114.12354,"新界葵涌 大隴街石文徑 金珮樓地下16B","Kwai Tsing","葵青","Light Refreshment","2026-06-30",[]],["fehd_3191000109","創記小食店","創記小食店",22.35884,114.12476,"新界葵涌 盛芳街19號地下 京寶大廈10A號鋪","Kwai Tsing","葵青","Light Refreshment","2026-06-30",[]],["fehd_3191000118","biesquared 咖啡店","bie2 Cafe",22.3603,114.12182,"新界葵涌 大隴街石文徑18B","Kwai Tsing","葵青","Light Refreshment","2026-06-30",[]],["fehd_3191000136","祥裕茶餐廳","祥裕茶餐廳",22.36185,114.1206,"新界葵涌 德士古道465地段443約 宏華大廈地下I座","Kwai Tsing","葵青","Light Refreshment","2026-06-30",[]],["fehd_3191000172","ELEPHANT KITCHEN","ELEPHANT KITCHEN",22.35839,114.12173,"新界葵涌梨木道102-116號 葵寶大廈LG樓3號鋪","Kwai Tsing","葵青","Light Refreshment","2026-06-30",[]],["fehd_3191000215","海豐牛腩粉麵","海豐牛腩粉麵",22.36296,114.12131,"新界葵涌 大隴街153號 怡勝花園地下3號鋪","Kwai Tsing","葵青","Light Refreshment","2026-06-30",[]],["fehd_3191000224","洪發","洪發",22.3631,114.12302,"新界葵涌 光輝圍11-13號 昌利大廈地下4A號鋪","Kwai Tsing","葵青","Light Refreshment","2026-06-30",[]],["fehd_3191000242","為食來車仔麵","為食來車仔麵",22.36198,114.12053,"新界葵涌和宜合道186-218號 誼發大廈地下34號鋪","Kwai Tsing","葵青","Light Refreshment","2026-09-04",[]],["fehd_3191000251","新苑記牛腩粉麵專家","新苑記牛腩粉麵專家",22.35834,114.12561,"新界葵涌 禾塘咀街119D號地下","Kwai Tsing","葵青","Light Refreshment","2026-09-13",[]],["fehd_3191000297","長樂小食店","長樂小食店",22.35939,114.12036,"新界青衣 細山路2-16號 美景花園商場第3層102號鋪","Kwai Tsing","葵青","Light Refreshment","2026-09-25",[]],["fehd_3191000303","雲南小鍋米線","雲南小鍋米線",22.36079,114.12126,"新界葵涌 梨木道112號 葵寶大廈LG樓5號鋪","Kwai Tsing","葵青","Light Refreshment","2027-05-27",[]],["fehd_3191000321","有口福","有口福",22.35974,114.12844,"新界葵涌 大隴街153號 怡勝花園地下2號鋪","Kwai Tsing","葵青","Light Refreshment","2026-08-09",[]],["fehd_3191000437","金輝麵食","金輝麵食",22.35671,114.12785,"新界葵涌 和宜合道82號地下","Kwai Tsing","葵青","Light Refreshment","2027-03-23",[]],["fehd_3191000464","酸．辣．燙","酸．辣．燙",22.36046,114.12641,"新界葵涌葵涌道1001號 德昌大廈地下24號鋪","Kwai Tsing","葵青","Light Refreshment","2026-11-16",[]],["fehd_3191000491","亞潘泰國菜","AMPORN THAI FOOD",22.35572,114.12917,"新界葵涌和宜合道5-27號 寶星中心地下6號鋪","Kwai Tsing","葵青","Light Refreshment","2027-03-05",[]],["fehd_3191000686","一品香","一品香",22.35719,114.12419,"新界葵涌 葵富路7-11號 葵涌廣場地下A08號鋪","Kwai Tsing","葵青","Light Refreshment","2026-12-30",[]],["fehd_3191000695","小雨天","小雨天",22.36105,114.12168,"新界葵涌 葵富路7-11號 葵涌廣場2字樓C33A,C35,C36及C37號鋪","Kwai Tsing","葵青","Light Refreshment","2027-02-22",[]],["fehd_3191000701","八方雲集鍋貼水餃專門店","八方雲集鍋貼水餃專門店",22.35768,114.12547,"新界葵涌 興芳路166-174號 新葵興商場1字樓10-11號單位","Kwai Tsing","葵青","Light Refreshment","2027-02-24",[]],["fehd_3191000756","地道館","地道館",22.36213,114.12009,"新界葵涌 葵涌廣場地下A09號鋪","Kwai Tsing","葵青","Light Refreshment","2027-04-12",[]],["fehd_3191000774","翠苑牛雜粉麵專家","翠苑牛雜粉麵專家",22.3644,114.12714,"新界葵涌 光輝圍21號 昌發大廈地下4號鋪","Kwai Tsing","葵青","Light Refreshment","2027-05-12",[]],["fehd_3191000862","街粥","街粥",22.35756,114.12509,"新界葵涌 大隴街129-137及141-151號 葵都大廈地下4號鋪","Kwai Tsing","葵青","Light Refreshment","2026-09-23",[]],["fehd_3191000871","棠記","棠記",22.36492,114.12464,"新界葵涌 禮芳街19號 葵福大廈地下","Kwai Tsing","葵青","Light Refreshment","2026-10-10",[]],["fehd_3191800013","甜品莊","甜品莊",22.35515,114.12637,"新界青衣翠怡花園商場 第2期地下G32號鋪","Kwai Tsing","葵青","Light Refreshment","2026-05-30",[]],["fehd_3191800208","麥呂號冰廳","麥呂號冰廳",22.363,114.1248,"新界葵涌 屏麗徑葵豐樓 5-11號地下 19B鋪","Kwai Tsing","葵青","Light Refreshment","2026-12-01",[]],["fehd_3191800244","德寳美食","德寳美食",22.35599,114.12948,"新界葵涌 青山公路410號 保基大樓地下13號鋪","Kwai Tsing","葵青","Light Refreshment","2027-04-18",[]],["fehd_3191800299","太平洋酒吧","Bar Pacific",22.35652,114.12337,"新界葵涌青山公路501-503及507-511號 友成大廈地下C,D及E鋪","Kwai Tsing","葵青","Light Refreshment","2026-11-13",[]],["fehd_3191800305","三寶小食","三寶小食",22.35515,114.12969,"新界葵涌葵富路7-11號 葵涌廣場地下A13A號鋪","Kwai Tsing","葵青","Light Refreshment","2027-01-25",[]],["fehd_3191800387","滋味棧","滋味棧",22.35607,114.12205,"新界葵涌德大徑8號德泰大廈地下F2號鋪","Kwai Tsing","葵青","Light Refreshment","2027-01-10",[]],["fehd_3191800402","三兄妹","三兄妹",22.35579,114.12966,"新界葵涌景荔徑8號 盈暉家居城1樓104號鋪","Kwai Tsing","葵青","Light Refreshment","2027-03-30",[]],["fehd_3191800420","太平洋酒吧","Bar Pacific",22.35728,114.12517,"新界葵涌葵芳榮芳路77-85號 葵樂大廈地下及閣樓D鋪","Kwai Tsing","葵青","Light Refreshment","2027-04-24",[]],["fehd_3191800509","初心","初心",22.35554,114.12648,"新界青衣美景花園L-3第8座35號鋪","Kwai Tsing","葵青","Light Refreshment","2027-05-31",[]],["fehd_3191800518","STARBUCKS COFFEE","STARBUCKS COFFEE",22.36207,114.12453,"新界青衣青衣城第一層166號鋪","Kwai Tsing","葵青","Light Refreshment","2027-07-15",[]],["fehd_3191800545","喜洋洋","喜洋洋",22.35813,114.12229,"新界葵涌葵盛東邨葵盛東商場地下5號鋪","Kwai Tsing","葵青","Light Refreshment","2027-02-21",[]],["fehd_3191800581","潮汕錦豐粉麵","潮汕錦豐粉麵",22.36262,114.12142,"新界葵涌打磚坪街1-25號寶星中心1樓5號鋪","Kwai Tsing","葵青","Light Refreshment","2026-09-05",[]],["fehd_3191800606","譚仔雲南米線","譚仔雲南米線",22.36169,114.12791,"新界葵涌葵芳興芳路198-200號葵豐大廈地下及部份閣樓","Kwai Tsing","葵青","Light Refreshment","2026-11-30",[]],["fehd_3191800624","伊勢堂","伊勢堂",22.35707,114.12106,"新界青衣細山路2-16號美景花園第三層114號鋪","Kwai Tsing","葵青","Light Refreshment","2027-02-21",["Sashimi","Sushi"]],["fehd_3191800679","川味美食","川味美食",22.36436,114.12903,"新界葵涌禮芳街1號及盛芳街38-44號寬德大廈地下2號鋪","Kwai Tsing","葵青","Light Refreshment","2026-10-02",[]],["fehd_3191800697","呢度","Here",22.36453,114.12475,"新界葵涌屏麗徑7號葵豐樓地下A鋪","Kwai Tsing","葵青","Light Refreshment","2027-02-27",[]],["fehd_3191800703","八方雲集","Bafong Yunji",22.36467,114.12533,"新界葵涌葵涌道1001號德昌大廈地下29號鋪","Kwai Tsing","葵青","Light Refreshment","2027-03-29",[]],["fehd_3191800721","泰禾小食","Thailand Food",22.35783,114.12459,"新界葵涌大隴街153號怡勝花園地下7號鋪","Kwai Tsing","葵青","Light Refreshment","2026-08-21",[]],["fehd_3191800730","泰星匯車仔麵","泰星匯車仔麵",22.36412,114.12785,"新界葵涌高芳街15-25號及信芳街39號悅龍大廈地下A1號鋪","Kwai Tsing","葵青","Light Refreshment","2026-09-06",[]],["fehd_3191800785","川味風","川味風",22.36031,114.12515,"新界葵涌葵盛西邨第7座地下2號舖","Kwai Tsing","葵青","Light Refreshment","2026-10-03",[]],["fehd_3191800800","Pacific Coffee Company","Pacific Coffee Company",22.36306,114.12126,"新界葵涌瑪嘉烈醫院主大樓地下","Kwai Tsing","葵青","Light Refreshment","2026-11-13",[]],["fehd_3191800828","正宗酸辣粉","正宗酸辣粉",22.35736,114.12403,"新界葵涌信芳街39號及高芳街15/25號 悅龍大廈地下A鋪A5部份","Kwai Tsing","葵青","Light Refreshment","2027-04-08",[]],["fehd_3191800846","樂景麵包茶餐廳","LOK KING RSTAURANT",22.35782,114.12282,"新界葵涌荔景邨樂景樓地下1號鋪(較大範圍)","Kwai Tsing","葵青","Light Refreshment","2026-07-31",[]],["fehd_3191800864","小上海","小上海",22.35539,114.1232,"新界葵涌梨木道112號葵寶大廈低層4號鋪","Kwai Tsing","葵青","Light Refreshment","2026-09-24",[]],["fehd_3191800873","爸辣小館","爸辣小館",22.36349,114.12349,"新界葵涌青山公路450-454號名賢大廈地下A鋪","Kwai Tsing","葵青","Light Refreshment","2026-12-23",[]],["fehd_3191800891","大福鮑魚小皇子","大福鮑魚小皇子",22.3645,114.12516,"新界葵涌和宜合道224-234A號葵富大廈地下6A鋪","Kwai Tsing","葵青","Light Refreshment","2027-02-05",[]],["fehd_3191800907","麵屋丸京","麵屋丸京",22.3623,114.12238,"新界葵涌盛芳街21號興芳路188-190號智芳街1-3號 協德大廈地下2號鋪","Kwai Tsing","葵青","Light Refreshment","2027-03-03",[]],["fehd_3191800925","新長樂小食店","新長樂小食店",22.35633,114.12195,"新界青衣長康邨康泰樓地下2號鋪","Kwai Tsing","葵青","Light Refreshment","2026-07-08",[]],["fehd_3191800989","八方雲集","八方雲集",22.35779,114.12307,"新界青衣青綠街7-19號青怡花園地下44號鋪","Kwai Tsing","葵青","Light Refreshment","2027-01-22",[]],["fehd_3191800998","醉鮮靚湯特色粉麵","醉鮮靚湯特色粉麵",22.36379,114.12213,"新界葵涌信芳街35-37號，禮芳街5-13及17-23號 葵福大廈地下6號鋪","Kwai Tsing","葵青","Light Refreshment","2027-02-04",[]],["fehd_3191801007","龍川上海料理","龍川上海料理",22.35789,114.12367,"新界葵涌光輝圍21號昌發大廈地下5號鋪","Kwai Tsing","葵青","Light Refreshment","2027-03-10",[]],["fehd_3191801016","順心糖水聚賢美食","順心糖水聚賢美食",22.36292,114.12955,"新界葵涌和宜合道202號誼發大廈1樓1A及2號鋪","Kwai Tsing","葵青","Light Refreshment","2027-05-04",[]],["fehd_3191801025","Starbucks Coffee","Starbucks Coffee",22.35566,114.12177,"新界葵涌興芳路223號新都會廣場2樓219A號鋪","Kwai Tsing","葵青","Light Refreshment","2026-06-28",[]],["fehd_3191801034","佰喜屋拉麵","佰喜屋拉麵",22.3559,114.12115,"新界葵涌和宜合道138-184號瑞景大廈地下12號鋪","Kwai Tsing","葵青","Light Refreshment","2026-07-16",[]],["fehd_3191801043","食臺","Stage gourmet",22.35647,114.12823,"新界葵涌榮芳路109號葵祥大廈地下E1室","Kwai Tsing","葵青","Light Refreshment","2026-08-25",[]],["fehd_3191801052","葵康車仔麵咖啡小食","葵康車仔麵咖啡小食",22.36359,114.12946,"新界葵涌上角街葵涌商場葵涌街市地下 59,60,61,62號鋪","Kwai Tsing","葵青","Light Refreshment","2026-08-30",[]],["fehd_3191801061","船麵","Aroydee Thai",22.35769,114.1281,"新界葵涌屏麗徑3,7-9及13-21號 青山公路葵涌段456-458號 葵豐樓地下J鋪(A部份)","Kwai Tsing","葵青","Light Refreshment","2026-09-07",[]],["fehd_3191801131","DELI-O","DELI-O",22.36391,114.12024,"新界葵涌   新葵興廣場 2樓1B鋪","Kwai Tsing","葵青","Light Refreshment","2026-12-15",[]],["fehd_3191801140","一志料理","一志料理",22.36494,114.12162,"新界葵涌和宜合道26-30號和宜商場地下24號鋪","Kwai Tsing","葵青","Light Refreshment","2027-01-19",["Sashimi","Sushi"]],["fehd_3191801159","么么茶","么么茶",22.36419,114.12126,"新界青衣細山路2-16號美景花園三樓99號鋪","Kwai Tsing","葵青","Light Refreshment","2027-02-04",[]],["fehd_3191801168","太平洋酒吧(第六十九分店)","BAR PACIFIC LXIX",22.35583,114.12422,"新界葵涌青山公路444-448號名堂大樓A座地下B&C鋪","Kwai Tsing","葵青","Light Refreshment","2027-02-04",["Karaoke"]],["fehd_3191801177","串串居","CHUAN CHUAN HOUSE",22.35667,114.12069,"新界葵涌葵涌道1009號珍寶大樓地下E鋪","Kwai Tsing","葵青","Light Refreshment","2027-04-27",[]],["fehd_3191801186","COZY CAFE CO.","COZY CAFE CO.",22.36274,114.12492,"新界葵涌打磚砰街1-25號寶星中心地下低層5鋪","Kwai Tsing","葵青","Light Refreshment","2027-05-17",[]],["fehd_3191801195","感味思路","SENSORY ZERO",22.36372,114.1291,"新界葵涌葵昌路100號KC100地下1號鋪及鋪前露天座位","Kwai Tsing","葵青","Light Refreshment","2026-08-23",["Outside Seating"]],["fehd_3191801210","三元米線","三元米線",22.35686,114.12869,"新界葵涌美芳街2-14號昌鴻大廈地下5號鋪","Kwai Tsing","葵青","Light Refreshment","2026-10-03",[]],["fehd_3191801247","利華超級三文治","Oliver's Super Sandwiches",22.36177,114.12588,"新界葵涌九龍貿易中心一樓S2鋪A部份及OS2B號鋪A部份","Kwai Tsing","葵青","Light Refreshment","2027-04-04",[]],["fehd_3191801265","八方雲集","八方雲集",22.35683,114.12781,"新界青衣担杆山路6號長發邨長發廣場3樓304及311鋪","Kwai Tsing","葵青","Light Refreshment","2027-06-01",[]],["fehd_3191801283","迎麵","Come noodle",22.35682,114.12503,"新界青衣美景花園第三層92-93號鋪","Kwai Tsing","葵青","Light Refreshment","2026-09-26",[]],["fehd_3191801292","裕一品","裕一品",22.36379,114.12492,"新界葵涌和宜合道186-218號 誼發大廈地下15號及27號鋪","Kwai Tsing","葵青","Light Refreshment","2026-10-02",[]],["fehd_3191801308","八方雲集","八方雲集",22.36265,114.12652,"新界葵涌榮芳路9號恆景花園恆景商場地下G05鋪","Kwai Tsing","葵青","Light Refreshment","2026-10-09",[]],["fehd_3191801317","上海坊","上海坊",22.35881,114.12678,"新界葵涌德士古道35-43號德泰大廈地下H1號鋪","Kwai Tsing","葵青","Light Refreshment","2026-12-12",[]],["fehd_3191801326","Toby’s Kitchen","Toby’s Kitchen",22.35693,114.12601,"新界葵涌大連排道132-134號TLP132地下","Kwai Tsing","葵青","Light Refreshment","2027-02-21",[]],["fehd_3191801353","影藝戲院 (青衣城)","Cine-Art House (Maritime Square)",22.36011,114.12193,"新界青衣青敬路31號青衣城3樓326室B部分","Kwai Tsing","葵青","Light Refreshment","2026-07-11",[]],["fehd_3191801362","Starbucks Coffee","Starbucks Coffee",22.36412,114.12632,"新界葵涌葵昌路72至76號活@KCC4樓408號鋪","Kwai Tsing","葵青","Light Refreshment","2026-10-01",[]],["fehd_3191801380","正咖啡","ZENGA COFFEE",22.36387,114.12037,"新界葵涌和宜合道138至184號瑞景大廈地下15鋪","Kwai Tsing","葵青","Light Refreshment","2026-11-27",[]],["fehd_3191801414","牛雜佬粉麵","牛雜佬粉麵",22.35674,114.12229,"新界葵涌禾塘咀街127-133號錦華樓地下D鋪","Kwai Tsing","葵青","Light Refreshment","2027-01-09",[]],["fehd_3191801423","美味車仔麵","Delicious Sweet Cart Noodle",22.35654,114.12261,"新界葵涌大廈街23號德泰大廈地下G3-G5號舖","Kwai Tsing","葵青","Light Refreshment","2027-02-17",[]],["fehd_3191801432","Little Prince","Little Prince",22.36386,114.1266,"新界葵涌葵昌路72-76號活@KCC地下G05號鋪","Kwai Tsing","葵青","Light Refreshment","2027-03-10",[]],["fehd_3191801487","瓜破菓子店","Uriwari",22.35874,114.12207,"新界葵涌葵昌路72-76號活@KCC四樓409號鋪","Kwai Tsing","葵青","Light Refreshment","2026-07-10",[]],["fehd_3191801496","嘉寶漢堡","KABO BURGER",22.3579,114.12365,"新界葵涌青山公路499號嘉寶大廈地下A及B1號鋪","Kwai Tsing","葵青","Light Refreshment","2026-07-22",[]],["fehd_3191801539","Arome Cafe","Arome Cafe",22.35759,114.12856,"新界葵芳新都會廣場2樓297-298鋪","Kwai Tsing","葵青","Light Refreshment","2026-11-25",[]],["fehd_3191801548","細妹姐餃子拉麵店","細妹姐餃子拉麵店",22.36288,114.12164,"新界葵涌葵富路7-11號葵涌廣場2樓C18-19鋪","Kwai Tsing","葵青","Light Refreshment","2027-03-04",[]],["fehd_3191801557","一口烘焙","BAKE & BITE",22.36275,114.12741,"新界青衣擔桿山路6號長發邨長發廣場2樓201A鋪(B部分)","Kwai Tsing","葵青","Light Refreshment","2027-03-23",[]],["fehd_3191801566","家館","Family Restaurant",22.36133,114.122,"新界葵涌光輝圍11-13號昌利樓地下3號鋪","Kwai Tsing","葵青","Light Refreshment","2027-04-16",[]],["fehd_3191801575","髀家Chill","髀家Chill",22.36455,114.1264,"新界葵涌青山公路539號昌宏大廈地下12號舖","Kwai Tsing","葵青","Light Refreshment","2027-05-01",[]],["fehd_3191801636","土耳其小城","SAFRANBOLU RESTAURANT",22.36087,114.12766,"新界葵涌敬祖路6號祖堯邨E座1樓107號鋪","Kwai Tsing","葵青","Light Refreshment","2026-10-25",[]],["fehd_3191801663","SUBWAY","SUBWAY",22.35729,114.12899,"新界葵涌葵昌路72-76號LIFE@KCC1樓107號鋪","Kwai Tsing","葵青","Light Refreshment","2027-01-24",[]],["fehd_3191801672","#湯o雞","#湯o雞",22.35854,114.12889,"新界葵涌葵富路7-11號葵涌廣場3樓302A號鋪","Kwai Tsing","葵青","Light Refreshment","2027-02-09",[]],["fehd_3191801681","百得阿姨","百得阿姨",22.35626,114.12331,"新界葵涌葵富路7-11號葵涌廣場1樓B35號鋪","Kwai Tsing","葵青","Light Refreshment","2027-02-28",[]],["fehd_3191801706","洪記麵家","HUNG KEE NOODLES",22.35895,114.12353,"新界青衣翠怡花園商場2期地下G08號鋪","Kwai Tsing","葵青","Light Refreshment","2026-05-24",[]],["fehd_3191801715","HANG OUT COFFEE","HANG OUT COFFEE",22.365,114.1287,"新界葵涌和宜合道1號葵星中心高層地下66C號鋪","Kwai Tsing","葵青","Light Refreshment","2027-05-29",[]],["fehd_3191801742","洪記麵家","HUNG KEE NOODLES",22.36294,114.12546,"新界葵涌葵盛東邨葵盛東邨商場一樓114J鋪","Kwai Tsing","葵青","Light Refreshment","2027-05-18",[]],["fehd_3191801760","新の千座","新の千座",22.35889,114.12776,"新界葵涌青山道456-458號屏麗徑3,7-9及13-21號 葵豐樓地下D號舖D2部份","Kwai Tsing","葵青","Light Refreshment","2026-07-11",[]],["fehd_3191801779","萌記牛什麵家","萌記牛什麵家",22.35564,114.12527,"新界葵涌葵富路7-11號葵涌廣場地下A16鋪","Kwai Tsing","葵青","Light Refreshment","2026-07-12",[]],["fehd_3191801788","樂麵","Lotmee",22.35726,114.12996,"新界葵涌興芳路223號新都會廣場第2層270-271號鋪","Kwai Tsing","葵青","Light Refreshment","2026-07-17",[]],["fehd_3191801797","KO'S COFFEE","KO'S COFFEE",22.3574,114.12972,"新界葵涌葵榮路30-34號EDGE地下G01號鋪","Kwai Tsing","葵青","Light Refreshment","2026-07-26",[]],["fehd_3191801803","初心食堂","SHOSHIN SHOKUDO",22.3565,114.12136,"新界葵涌美芳街8號昌鴻大廈地下9鋪","Kwai Tsing","葵青","Light Refreshment","2026-07-31",[]],["fehd_3191801812","KINGS GARDEN LIMITED","KINGS GARDEN LIMITED",22.3556,114.12483,"新界葵涌葵昌路51號九龍貿易中心LEVEL 1 OS1A號鋪","Kwai Tsing","葵青","Light Refreshment","2026-08-06",[]],["fehd_3191801821","杏甜品","Almond Dessert",22.35809,114.12807,"新界葵涌興芳路223號新都會廣場第4層477-478號鋪","Kwai Tsing","葵青","Light Refreshment","2026-08-14",[]],["fehd_3191801830","85℃","85℃",22.3571,114.12705,"新界葵涌興芳街177號葵芳廣場1樓116B號鋪","Kwai Tsing","葵青","Light Refreshment","2026-09-04",[]],["fehd_3191801849","食得喜麵家","食得喜麵家",22.36308,114.1296,"新界青衣青康路12號長康邨商場一期 康貴樓地下10號舖","Kwai Tsing","葵青","Light Refreshment","2026-09-14",[]],["fehd_3191801876","榮海牛腩粉麵","榮海牛腩粉麵",22.36447,114.12057,"新界葵涌大窩口邨商業/停車場大樓(又名大窩口商業中心1座) 街市1樓27-28號檔","Kwai Tsing","葵青","Light Refreshment","2027-01-29",[]],["fehd_3191801885","福食","Fu Shi",22.35856,114.12701,"新界葵涌貨櫃碼頭路77-81號MAGNET PLACE 第一座地下1號舗及1號舗對出座位間","Kwai Tsing","葵青","Light Refreshment","2027-02-28",[]],["fehd_3191801894","曼利","Money",22.36102,114.12019,"新界葵涌光輝圍39A號昌偉大廈地下27號","Kwai Tsing","葵青","Light Refreshment","2027-03-06",[]],["fehd_3191801900","喜由此你","C FOR U",22.35975,114.12333,"新界葵涌葵涌道1001號德昌大廈地下14號鋪","Kwai Tsing","葵青","Light Refreshment","2027-03-21",[]],["fehd_3191801919","SUBWAY","SUBWAY",22.35782,114.12093,"新界葵涌圍乪街6號石籬邨石籬商場及街市 (又稱為石籬商場(一期)(商業/停車場大樓的部份)) 1樓A104號鋪","Kwai Tsing","葵青","Light Refreshment","2027-04-22",[]],["fehd_3191801928","樂園麵家","樂園麵家",22.35909,114.12136,"新界葵青葵涌安足街7號安蔭商場1樓112-113號鋪","Kwai Tsing","葵青","Light Refreshment","2027-05-02",[]],["fehd_3191801937","SOYMYLK","SOYMYLK",22.35668,114.1289,"新界葵涌興芳路223號新都會廣場4樓493A號鋪","Kwai Tsing","葵青","Light Refreshment","2027-06-13",[]],["fehd_3191801946","順發牛雜粉麵","順發牛雜粉麵",22.36304,114.12032,"新界葵涌葵涌邨葵涌街市地下63至66號檔","Kwai Tsing","葵青","Light Refreshment","2026-07-22",[]],["fehd_3191801964","豐食記","FENGSHIJI",22.36353,114.12957,"新界青衣長康邨二期商場地下102號鋪","Kwai Tsing","葵青","Light Refreshment","2026-08-19",[]],["fehd_3191801973","潮龍園","潮龍園",22.3614,114.12678,"新界葵涌興芳路177號葵芳邨葵芳廣場地下6號鋪","Kwai Tsing","葵青","Light Refreshment","2026-09-02",[]],["fehd_3191801982","熊貓小雲吞","PANDA WONTON",22.36203,114.12742,"新界葵涌大隴街110號石籬商場一期1樓A107A號舖","Kwai Tsing","葵青","Light Refreshment","2026-11-10",[]],["fehd_3191802000","Pho M Cafe","Pho M Cafe",22.36304,114.12248,"新界葵涌青山公路438-442號名德大廈地下ID 及IE鋪","Kwai Tsing","葵青","Light Refreshment","2027-02-19",[]],["fehd_3191802019","金潮興牛雜粉麵專家","金潮興牛雜粉麵專家",22.36206,114.12712,"新界青衣牙鷹洲街8號灝景灣商場第1層2號鋪","Kwai Tsing","葵青","Light Refreshment","2027-04-07",[]],["fehd_3191802028","百年牛雜粉麵專家","百年牛雜粉麵專家",22.36186,114.12104,"新界青衣担杆山路6號長發邨長發廣場地下13-14鋪","Kwai Tsing","葵青","Light Refreshment","2027-04-21",[]],["fehd_3191802037","潮得起","潮得起",22.36052,114.12947,"新界葵涌圍乪街6號石籬商埸一期 1樓A109A號鋪","Kwai Tsing","葵青","Light Refreshment","2026-05-27",[]],["fehd_3191802046","輝記小廚","輝記小廚",22.35947,114.12705,"新界葵涌安足街7號安蔭邨安蔭邨商場9-13及15-19號 地下一斗農林水產(安蔭)M2號檔位","Kwai Tsing","葵青","Light Refreshment","2026-06-26",[]],["fehd_3191802055","袁記雲餃","Yuanji Dumpling",22.35506,114.12167,"新界葵涌和宜合道50-56號葵涌花園低層地下5A及5B號舖","Kwai Tsing","葵青","Light Refreshment","2026-07-09",[]],["fehd_3191802064","榮海牛腩粉麵","榮海牛腩粉麵",22.35852,114.12469,"新界葵青葵涌  葵盛東邨 葵盛東商場 地下葵盛東街巿K-KSE3-5號舖","Kwai Tsing","葵青","Light Refreshment","2026-07-23",[]],["fehd_3191802073","木屋小食店","木屋小食店",22.36205,114.12662,"新界青衣長康邨康泰樓地下4號鋪","Kwai Tsing","葵青","Light Refreshment","2026-08-13",[]],["fehd_3191802082","王子雞","王子雞",22.35703,114.12971,"新界葵涌  仁芳街2-14號 美豐大廈 地下 9號鋪","Kwai Tsing","葵青","Light Refreshment","2026-10-02",[]],["fehd_3191802091","永年士多","WING NIN NOODLE",22.35749,114.12627,"新界青衣青敬路33號青衣城地下G26-27號舖","Kwai Tsing","葵青","Light Refreshment","2026-12-04",[]],["fehd_3191802107","研香","GRINDIE",22.36412,114.12163,"新界青衣青敬路31號青衣城2期1樓186-187號舖","Kwai Tsing","葵青","Light Refreshment","2026-12-22",[]],["fehd_3191802116","越滿","越滿",22.3621,114.12522,"新界葵青葵涌 美芳街2-14號  昌鴻大廈 地下1號鋪","Kwai Tsing","葵青","Light Refreshment","2027-02-02",[]],["fehd_3191802125","袁記雲餃","袁記雲餃",22.35847,114.12108,"新界葵青葵涌 葵興路100-102號   葵涌中心 地下A03 及 A04號舖","Kwai Tsing","葵青","Light Refreshment","2027-03-22",[]],["fehd_3191802134","五谷漁粉","五谷漁粉",22.35852,114.12422,"新界葵涌葵涌道1001號德昌大廈地下23A號鋪","Kwai Tsing","葵青","Light Refreshment","2027-05-07",[]],["fehd_3991802178","沒有記錄","No Record",22.35998,114.12904,"新界葵涌安足街7號安蔭邨安蔭商場地下 M3-M13號鋪","Kwai Tsing","葵青","Light Refreshment","2026-07-21",[]],["fehd_3991802187","NEKOKA CAFE'","NEKOKA CAFE'",22.35509,114.12359,"新界青衣細山路2-16號美景花園商場第3層1&20鋪","Kwai Tsing","葵青","Light Refreshment","2026-09-30",[]],["fehd_3991802196","吃茶三千","CHICHA San Chen",22.36048,114.12773,"新界青衣青敬路33號青衣城第1層128號舖","Kwai Tsing","葵青","Light Refreshment","2026-09-30",[]],["fehd_3991802202","cafe330","cafe330",22.35809,114.12621,"新界葵涌 葵涌醫院路3-15號  葵涌醫院 DE座 2樓 A部分","Kwai Tsing","葵青","Light Refreshment","2026-10-08",[]],["fehd_3991802211","沒有記錄","No Record",22.3612,114.12658,"新界葵涌葵富路7-11號葵涌廣場地下A38A鋪","Kwai Tsing","葵青","Light Refreshment","2026-10-14",[]],["fehd_3991802220","沒有記錄","No Record",22.3588,114.12593,"新界葵涌葵富路7-11號葵涌廣場地下A15A號鋪","Kwai Tsing","葵青","Light Refreshment","2026-10-15",[]]]}